Workbook

Sheet Admin_Inputs
A2: Drivers de l'Opération | E2: Drivers d'Exploitation | I2: Drivers de Financement
A3: Driver | B3: Valeur | E3: Driver | F3: Valeur | I3: Driver | J3: Valeur
A4: Multiple d'Entrée (EV/EBITDA) | B4: =_xlfn.XLOOKUP(Setup!E4, SectBenchTable[sector], SectBenchTable[target_ebitda_mult]) -> 9.5 | E4: Croissance Annuelle du Revenu | F4: =_xlfn.XLOOKUP(Setup!B2, Table_Data[symbol], Table_Data[avg_revenue_growth]) -> 0.1418 | I4: Taux d'Intérêt (%) | J4: 0.08
A5: Frais de Transaction (%) | B5: 0.03 | E5: Marge d'EBITDA Cible | F5: =_xlfn.XLOOKUP(Setup!E4, SectBenchTable[sector], SectBenchTable[ebitda_margin_target]) -> 0.18 | I5: Taux d'Impôt (IS) | J5: =_xlfn.XLOOKUP(Setup!E5,TaxTable[country_name],TaxTable[tax_rate] ) -> 0.25
A6: Levier Senior (x EBITDA) | B6: 5x | E6: Intensité du Capex (%) | F6: =Setup!E9 -> 0.0159 | I6: Horizon de Détention | J6: 5
A7: Management Roll-over (%) | B7: 0.15 | E7: Variation du BFR (% CA) | F7: =_xlfn.XLOOKUP(Setup!E4, SectBenchTable[sector], SectBenchTable[nwc_variation_revenue]) -> 0.08 | I7: Multiple de Sortie | J7: =B4 -> 9.5

Sheet Setup
B2: ACS.MC | D2: Métrique | E2: Valeur
B3: SELECTION | D3: Nom de l'entreprise | E3: =_xlfn.XLOOKUP($B$2, Table_Data[symbol], Table_Data[name]) -> ACS, Actividades de Construcción y Servicios, S.A.
D4: Secteur | E4: =_xlfn.XLOOKUP(B2,Table_Data[symbol], Table_Data[sector]) -> Industrials
D5: Country | E5: =_xlfn.XLOOKUP(B2,Table_Data[symbol], Table_Data[country]) -> Spain
D6: EBITDA (T0) | E6: =_xlfn.XLOOKUP($B$2, Table_Data[symbol], Table_Data[EBITDA]) -> 2702859000
D7: Dette Nette (T0) | E7: =_xlfn.XLOOKUP($B$2, Table_Data[symbol], Table_Data[Net_Debt]) -> 2791044000
D8: SAI Score | E8: =_xlfn.XLOOKUP($B$2, Table_Data[symbol], Table_Data[SAI_Score]) -> 11.443139
D9: Capex Intensity | E9: =_xlfn.XLOOKUP($B$2, Table_Data[symbol], Table_Data[capex_intensity]) -> 0.0159
D10: Cap | E10: =_xlfn.XLOOKUP(Setup!B2, Table_Data[symbol], Table_Data[market_cap]) -> 27067064320

Sheet LBO_Temp
B2: LBO | C2: =Setup!E3 -> ACS, Actividades de Construcción y Servicios, S.A.
B4: Hypothèses
B6: Entry | G6: Financials | L6: Capital Structure | N6: Montant | O6: Coût
B7: LTM EBITDA | E7: =J9 -> 2702859000 | G7: LTM Financials | L7: Dette Bancaire | N7: 4 | O7: 0.06
B8: EBITDA Multiple | E8: =AVERAGE(Admin_Inputs!B4, _xlfn.XLOOKUP(Setup!B2, Table_Data[symbol], Table_Data[RealMultiple])) -> 9.7571173 | G8: Chiffre d'Affaires | J8: =_xlfn.XLOOKUP(Setup!B2, Table_Data[symbol], Table_Data[Revenue]) -> 41633120000 | L8: Obligations Senior | N8: 2 | O8: 0.12
B9: Valeur d'Entreprise | E9: =E7*E8 -> 26372112410 | G9: EBITDA | J9: =Setup!E6 -> 2702859000
B10: Dette Nette Existante | E10: =Setup!E7 -> 2791044000 | G10: D&A | J10: =_xlfn.XLOOKUP(Setup!B2, Table_Data[symbol], Table_Data[depreciation_amortization]) -> 969658000 | L10: For Reference
B11: Valeur des Fonds Propres | E11: =E9-E10 -> 23581068410 | G11: Capex | J11: =_xlfn.XLOOKUP(Setup!B2, Table_Data[symbol], Table_Data[Capex]) -> 612491000 | L11: TRI | O11: =O106 -> 0.29725109
G12: BFR | J12: =Setup!E6 -LBO_Temp!J11-(_xlfn.XLOOKUP(Setup!B2, Table_Data[symbol], Table_Data[fcf_yield]))*Setup!E10 -> -2.2657271e+08
B13: Frais et commissions | E13: =J8*Admin_Inputs!B5 -> 1248993600
G14: Operating Assumptions
B15: Sortie | G15: Revenue Growth | J15: =(Admin_Inputs!F4+ (_xlfn.XLOOKUP(Setup!E4, SectBenchTable[sector], SectBenchTable[annual_growth])))/2 -> 0.0884
B16: EBITDA Multiple | E16: =E8 -> 9.7571173 | G16: YoY margin expansion | J16: 0.003
G17: Tax Rate | J17: =Admin_Inputs!J5 -> 0.25
B19: Ressources et Emplois
B21: Ressources | J21: Emplois
E22: Monant | F22: xEBITDA | G22: % Capital | M22: Monant | N22: xEBITDA | O22: % Capital
B23: =L7 -> Dette Bancaire | E23: =F23*$J$9 -> 10811436000 | F23: =N7 -> 4 | G23: =E23/$E$29 -> 0.39141937 | J23: Remboursement de la dette | M23: =E10 -> 2791044000 | N23: =M23/$J$9 -> 1.0326266 | O23: =M23/$M$29 -> 0.10104751
B24: =L8 -> Obligations Senior | E24: =F24*$J$9 -> 5405718000 | F24: =N8 -> 2 | G24: =E24/$E$29 -> 0.19570969 | J24: Paiement des titres | M24: =E11 -> 23581068410 | N24: =M24/$J$9 -> 8.7244908 | O24: =M24/$M$29 -> 0.85373368
B25: Total Debt | E25: =E23+E24 -> 16217154000 | F25: =E25/J9 -> 6 | G25: =E25/$E$29 -> 0.58712906
J26: Frais et commissions | M26: =E13 -> 1248993600 | N26: =M26/$J$9 -> 0.46210091 | O26: =M26/$M$29 -> 0.045218812
B27: Apport en fonds propres | E27: =E29-E25 -> 11403952010 | F27: =E27/J9 -> 4.2192182 | G27: =E27/$E$29 -> 0.41287094
B29: Total Sources | E29: =M29 -> 27621106010 | F29: =E29/J9 -> 10.219218 | G29: =E29/$E$29 -> 1 | J29: Total Uses | M29: =M23+M24+M26 -> 27621106010 | N29: =N23+N24+N26 -> 10.219218 | O29: =M29/$M$29 -> 1
B32: Financials
B34: Operating Model | J34: Year 0 | K34: Year 1 | L34: Year 2 | M34: Year 3 | N34: Year 4 | O34: Year 5
B35: Revenue | J35: =J8 -> 41633120000 | K35: =J35*(1+K36) -> 45313487808 | L35: =K35*(1+L36) -> 4.93192e+10 | M35: =L35*(1+M36) -> 5.3679017e+10 | N35: =M35*(1+N36) -> 5.8424243e+10 | O35: =N35*(1+O36) -> 6.3588946e+10
B36: % growth | K36: =$J$15 -> 0.0884 | L36: =K36 -> 0.0884 | M36: =L36 -> 0.0884 | N36: =M36 -> 0.0884 | O36: =N36 -> 0.0884
B38: EBITDA | J38: =J9 -> 2702859000 | K38: =K39*K35 -> 3.0777322e+09 | L38: =L39*L35 -> 3.4977613e+09 | M38: =M39*M35 -> 3.9680005e+09 | N38: =N39*N35 -> 4.4940444e+09 | O38: =O39*O35 -> 5.0820848e+09
B39: % sales | J39: =J38/J35 -> 0.064920885 | K39: =J39+$J$16 -> 0.067920885 | L39: =K39+$J$16 -> 0.070920885 | M39: =L39+$J$16 -> 0.073920885 | N39: =M39+$J$16 -> 0.076920885 | O39: =N39+$J$16 -> 0.079920885
B41: EBIT | J41: =J38-J56 -> 1733201000 | K41: =K38-K56 -> 2.0223564e+09 | L41: =L38-L56 -> 2.3490903e+09 | M41: =M38-M56 -> 2.717787e+09 | N41: =N38-N56 -> 3.1333121e+09 | O41: =O38-O56 -> 3.6010637e+09
B42: % sales | J42: =J41/J35 -> 0.041630341 | K42: =K41/K35 -> 0.044630341 | L42: =L41/L35 -> 0.047630341 | M42: =M41/M35 -> 0.050630341 | N42: =N41/N35 -> 0.053630341 | O42: =O41/O35 -> 0.056630341
B44: Interest | K44: =K91 -> 1297372320 | L44: =L91 -> 1.2402219e+09 | M44: =M91 -> 1.1636285e+09 | N44: =N91 -> 1.0646373e+09 | O44: =O91 -> 9.3992448e+08
B46: EBT | K46: =K41-K44 -> 7.2498411e+08 | L46: =L41-L44 -> 1.1088685e+09 | M46: =M41-M44 -> 1.5541585e+09 | N46: =N41-N44 -> 2.0686748e+09 | O46: =O41-O44 -> 2.6611392e+09
B47: % sales | K47: =K46/K35 -> 0.015999301 | L47: =L46/L35 -> 0.022483505 | M47: =M46/M35 -> 0.028952812 | N47: =N46/N35 -> 0.035407815 | O47: =O46/O35 -> 0.041849085
B49: Taxes | K49: =K46*K50 -> 1.8124603e+08 | L49: =L46*L50 -> 2.7721712e+08 | M49: =M46*M50 -> 3.8853962e+08 | N49: =N46*N50 -> 5.171687e+08 | O49: =O46*O50 -> 6.652848e+08
B50: % tax rate | K50: =J17 -> 0.25 | L50: =K50 -> 0.25 | M50: =L50 -> 0.25 | N50: =M50 -> 0.25 | O50: =N50 -> 0.25
B52: Net Income | K52: =K46-K49 -> 5.4373808e+08 | L52: =L46-L49 -> 8.3165136e+08 | M52: =M46-M49 -> 1.1656189e+09 | N52: =N46-N49 -> 1.5515061e+09 | O52: =O46-O49 -> 1.9958544e+09
B53: % sales | K53: =K52/K35 -> 0.011999475 | L53: =L52/L35 -> 0.016862629 | M53: =M52/M35 -> 0.021714609 | N53: =N52/N35 -> 0.026555861 | O53: =O52/O35 -> 0.031386814
B55: Cash flow Items | J55: Year 0 | K55: Year 1 | L55: Year 2 | M55: Year 3 | N55: Year 4 | O55: Year 5
B56: D&A | J56: =J10 -> 969658000 | K56: =K57*K35 -> 1.0553758e+09 | L56: =L57*L35 -> 1.148671e+09 | M56: =M57*M35 -> 1.2502135e+09 | N56: =N57*N35 -> 1.3607324e+09 | O56: =O57*O35 -> 1.4810211e+09
B57: % sales | J57: =J56/J35 -> 0.023290544 | K57: =J57 -> 0.023290544 | L57: =K57 -> 0.023290544 | M57: =L57 -> 0.023290544 | N57: =M57 -> 0.023290544 | O57: =N57 -> 0.023290544
B59: Net Working Capital | J59: =J12 -> -2.2657271e+08 | K59: =K60*K35 -> -2.4660173e+08 | L59: =L60*L35 -> -2.6840133e+08 | M59: =M60*M35 -> -2.92128e+08 | N59: =N60*N35 -> -3.1795212e+08 | O59: =O60*O35 -> -3.4605909e+08
B60: % sales | J60: =J59/J35 -> -0.0054421265 | K60: =J60 -> -0.0054421265 | L60: =K60 -> -0.0054421265 | M60: =L60 -> -0.0054421265 | N60: =M60 -> -0.0054421265 | O60: =N60 -> -0.0054421265
B61: Change in Net Working Capital | K61: =K59-J59 -> -20029027 | L61: =L59-K59 -> -21799593 | M61: =M59-L59 -> -23726677 | N61: =N59-M59 -> -25824116 | O61: =O59-N59 -> -28106967
B63: CapEx | J63: =J11 -> 612491000 | K63: =K64*K35 -> 6.666352e+08 | L63: =L64*L35 -> 7.2556576e+08 | M63: =M64*M35 -> 7.8970577e+08 | N63: =N64*N35 -> 8.5951576e+08 | O63: =O64*O35 -> 9.3549695e+08
B64: % sales | J64: =J63/J35 -> 0.014711629 | K64: =J64 -> 0.014711629 | L64: =K64 -> 0.014711629 | M64: =L64 -> 0.014711629 | N64: =M64 -> 0.014711629 | O64: =N64 -> 0.014711629
B66: Levered Cash Flow | J66: Year 0 | K66: Year 1 | L66: Year 2 | M66: Year 3 | N66: Year 4 | O66: Year 5
B67: Net Income | K67: =K52 -> 5.4373808e+08 | L67: =L52 -> 8.3165136e+08 | M67: =M52 -> 1.1656189e+09 | N67: =N52 -> 1.5515061e+09 | O67: =O52 -> 1.9958544e+09
B68: D&A | K68: =K56 -> 1.0553758e+09 | L68: =L56 -> 1.148671e+09 | M68: =M56 -> 1.2502135e+09 | N68: =N56 -> 1.3607324e+09 | O68: =O56 -> 1.4810211e+09
B69: CapEx | K69: =K63 -> 6.666352e+08 | L69: =L63 -> 7.2556576e+08 | M69: =M63 -> 7.8970577e+08 | N69: =N63 -> 8.5951576e+08 | O69: =O63 -> 9.3549695e+08
B70: Change in NWC | K70: =K61 -> -20029027 | L70: =L61 -> -21799593 | M70: =M61 -> -23726677 | N70: =N61 -> -25824116 | O70: =O61 -> -28106967
B71: Levered Cash Flow | K71: =K67+K68-K69-K70 -> 9.5250767e+08 | L71: =L67+L68-L69-L70 -> 1.2765562e+09 | M71: =M67+M68-M69-M70 -> 1.6498533e+09 | N71: =N67+N68-N69-N70 -> 2.0785468e+09 | O71: =O67+O68-O69-O70 -> 2.5694855e+09
B74: Debt Schedule
J76: Year 0 | K76: Year 1 | L76: Year 2 | M76: Year 3 | N76: Year 4 | O76: Year 5
B77: Bank Debt
B78: Beginning Balance | K78: =J81 -> 10811436000 | L78: =K81 -> 9.8589283e+09 | M78: =L81 -> 8.5823721e+09 | N78: =M81 -> 6.9325189e+09 | O78: =N81 -> 4.8539721e+09
B79: Interest | K79: =K78*$O$7 -> 648686160 | L79: =L78*$O$7 -> 5.915357e+08 | M79: =M78*$O$7 -> 5.1494233e+08 | N79: =N78*$O$7 -> 4.1595113e+08 | O79: =O78*$O$7 -> 2.9123832e+08
B80: Paydown | K80: =MIN(K71,K78) -> 9.5250767e+08 | L80: =MIN(L71,L78) -> 1.2765562e+09 | M80: =MIN(M71,M78) -> 1.6498533e+09 | N80: =MIN(N71,N78) -> 2.0785468e+09 | O80: =MIN(O71,O78) -> 2.5694855e+09
B81: Ending Balance | J81: =E23 -> 10811436000 | K81: =K78-K80 -> 9.8589283e+09 | L81: =L78-L80 -> 8.5823721e+09 | M81: =M78-M80 -> 6.9325189e+09 | N81: =N78-N80 -> 4.8539721e+09 | O81: =O78-O80 -> 2.2844865e+09
B83: Sr. Notes
B84: Beginning Balance | K84: =J87 -> 5405718000 | L84: =K87 -> 5405718000 | M84: =L87 -> 5405718000 | N84: =M87 -> 5405718000 | O84: =N87 -> 5405718000
B85: Interest | K85: =K84*$O$8 -> 648686160 | L85: =L84*$O$8 -> 648686160 | M85: =M84*$O$8 -> 648686160 | N85: =N84*$O$8 -> 648686160 | O85: =O84*$O$8 -> 648686160
B86: Paydown | K86: =MIN(K71,K71-K80) -> 0 | L86: =MIN(L71,L71-L80) -> 0 | M86: =MIN(M71,M71-M80) -> 0 | N86: =MIN(N71,N71-N80) -> 0 | O86: =MIN(O71,O71-O80) -> 0
B87: Ending Balance | J87: =E24 -> 5405718000 | K87: =K84-K86 -> 5405718000 | L87: =L84-L86 -> 5405718000 | M87: =M84-M86 -> 5405718000 | N87: =N84-N86 -> 5405718000 | O87: =O84-O86 -> 5405718000
B89: Total Debt
B90: Beginning Balance | K90: =K78+K84 -> 16217154000 | L90: =L78+L84 -> 1.5264646e+10 | M90: =M78+M84 -> 1.398809e+10 | N90: =N78+N84 -> 1.2338237e+10 | O90: =O78+O84 -> 1.025969e+10
B91: Interest | K91: =K79+K85 -> 1297372320 | L91: =L79+L85 -> 1.2402219e+09 | M91: =M79+M85 -> 1.1636285e+09 | N91: =N79+N85 -> 1.0646373e+09 | O91: =O79+O85 -> 9.3992448e+08
B92: Paydown | K92: =K80+K86 -> 9.5250767e+08 | L92: =L80+L86 -> 1.2765562e+09 | M92: =M80+M86 -> 1.6498533e+09 | N92: =N80+N86 -> 2.0785468e+09 | O92: =O80+O86 -> 2.5694855e+09
B93: Ending Balance | J93: =J81+J87 -> 16217154000 | K93: =K81+K87 -> 1.5264646e+10 | L93: =L81+L87 -> 1.398809e+10 | M93: =M81+M87 -> 1.2338237e+10 | N93: =N81+N87 -> 1.025969e+10 | O93: =O81+O87 -> 7.6902045e+09
B95: IRR
B97: EBITDA at Exit | O97: =O38 -> 5.0820848e+09
B98: Exit Multiple | O98: =E16 -> 9.7571173
B99: Enterprise Value | O99: =O97*O98 -> 4.9586498e+10
B100: Net Debt | O100: =O93 -> 7.6902045e+09
B101: Sponsor Equity Value | O101: =O99-O100 -> 4.1896293e+10
B103: Sponsor Equity at Entry | O103: =E27 -> 11403952010
B105: MOIC | O105: =O101/O103 -> 3.6738399
B106: TRI | O106: =O105^(1/5)-1 -> 0.29725109

Sheet dim_company
A1: Company_ID | B1: symbol | C1: name | D1: sector | E1: country | F1: market_cap | G1: ebitda_margin | H1: fcf_yield | I1: net_debt_ebitda | J1: capex_intensity | K1: dscr | L1: avg_revenue_growth | M1: volatility | N1: depreciation_amortization | O1: ev_ebitda | P1: Fiscal_Year | Q1: Revenue | R1: EBITDA | S1: EBIT | T1: Net_Income | U1: Total_Assets | V1: Total_Debt | W1: Cash | X1: Net_Debt | Y1: Capex | Z1: Date | AA1: Share_Price | AB1: Shares_Outstanding | AC1: LBO_Score | AD1: Op_Efficiency_Score | AE1: Deep_Value_Score | AF1: Bankruptcy_Risk_AltmanZ | AG1: Score_Serviceability | AH1: Score_Optimization | AI1: Score_Collateral | AJ1: SAI_Score | AK1: RealMultiple
A2: 1 | B2: JUN3.DE | C2: Jungheinrich Aktiengesellschaft | D2: Industrials | E2: Germany | F2: 3119160064 | G2: 0.1685 | H2: 0.1409 | I2: 0.19 | J2: 0.0257 | K2: 24.45 | L2: 0.0867 | N2: 467553000 | O2: 15.49 | P2: 2024 | Q2: 5391884000 | R2: 908550000 | S2: 440997000 | T2: 288993000 | U2: 7128360000 | V2: 696129000 | W2: 524856000 | X2: 171273000 | Y2: 138426000 | Z2: 46083 | AA2: 31.2 | AB2: 48000000 | AC2: 18.6098 | AD2: 6.4763 | AE2: 16.7046 | AF2: 0.2855 | AG2: 18.609843 | AH2: 6.4763356 | AI2: 16.704625 | AJ2: 14.398226 | AK2: 3.4331188
A3: 52 | B3: AALB.AS | C3: Aalberts N.V. | D3: Industrials | E3: Netherlands | F3: 3595531264 | G3: 0.1623 | H3: 0.0472 | I3: 1.17 | J3: 0.0835 | K3: 16.49 | L3: -0.014 | N3: 225800000 | O3: 9.16 | P3: 2024 | Q3: 3148600000 | R3: 511100000 | S3: 292600000 | T3: 179100000 | U3: 4230000000 | V3: 686600000 | W3: 89800000 | X3: 596800000 | Y3: 262900000 | Z3: 46083 | AA3: 34.68 | AB3: 108035683 | AC3: 14.0664 | AD3: 6.2748 | AE3: 10.2703 | AF3: -0.4412 | AG3: 14.0664 | AH3: 6.2748324 | AI3: 10.270256 | AJ3: 10.590087 | AK3: 7.034888
A4: 2 | B4: VIS.MC | C4: Viscofan, S.A. | D4: Consumer Cyclical | E4: Spain | F4: 2669550080 | G4: 0.2497 | H4: 0.0602 | I4: 0.52 | J4: 0.0623 | K4: 28.99 | L4: 0.0142 | N4: 85196000 | O4: 10.11 | P4: 2024 | Q4: 1203994000 | R4: 300602000 | S4: 216808000 | T4: 157019000 | U4: 1402848000 | V4: 212951000 | W4: 55143000 | X4: 157808000 | Y4: 75027000 | Z4: 46083 | AA4: 58 | AB4: 45746258 | AC4: 14.6968 | AD4: 9.1154 | AE4: 13.6114 | AF4: 0.0719 | AG4: 14.69676 | AH4: 9.1153768 | AI4: 13.611411 | AJ4: 12.696741 | AK4: 8.8806797
A5: 4 | B5: UBI.PA | C5: Ubisoft Entertainment SA | D5: Communication Services | E5: France | F5: 541744832 | G5: 0.3529 | H5: 0.2342 | I5: 1.75 | J5: 0.0221 | K5: 6.31 | L5: -0.0176 | N5: 710700000 | O5: -11.95 | P5: 2024 | Q5: 2300900000 | R5: 1105500000 | S5: 329400000 | T5: 157800000 | U5: 5121600000 | V5: 2509400000 | W5: 1205200000 | X5: 1304200000 | Y5: 116200000 | Z5: 46083 | AA5: 4.125 | AB5: 134728884 | AC5: 23.1339 | AD5: 12.4694 | AE5: 8.6224 | AF5: -0.2986 | AG5: 23.133891 | AH5: 12.469429 | AI5: 8.6223892 | AJ5: 15.581102 | AK5: 0.49004508
A6: 3 | B6: GRG.L | C6: Greggs plc | D6: Consumer Cyclical | E6: United Kingdom | F6: 1671173760 | G6: 0.1776 | H6: 0.0419 | I6: 0.81 | J6: 0.1196 | K6: 25.74 | L6: 0.1799 | N6: 140000000 | O6: 7.4 | P6: 2024 | Q6: 2014400000 | R6: 357800000 | S6: 217800000 | T6: 153400000 | U6: 1319700000 | V6: 415100000 | W6: 125300000 | X6: 289800000 | Y6: 240900000 | Z6: 46083 | AA6: 1559 | AB6: 101838742 | AC6: 13.8094 | AD6: 6.7721 | AE6: 11.8243 | AF6: -0.2142 | AG6: 13.809407 | AH6: 6.7720902 | AI6: 11.824255 | AJ6: 11.102666 | AK6: 4.6706925
A7: 136 | B7: ACKB.BR | C7: Ackermans & Van Haaren NV | D7: Industrials | E7: Belgium | F7: 8962184192 | G7: 0.2065 | H7: 0.1227 | I7: 5.34 | J7: 0.0513 | L7: 0.1101 | N7: 536485000 | O7: 8.3 | P7: 2024 | Q7: 6043334000 | R7: 1248085000 | S7: 807748000 | T7: 459871000 | U7: 20291367000 | V7: 9953790000 | W7: 3292681000 | X7: 6661109000 | Y7: 310160000 | Z7: 46085 | AA7: 274.4 | AB7: 32728537 | AC7: 17.7273 | AD7: 7.7114 | AE7: 5.1313 | AF7: -2.7844 | AG7: 17.727339 | AH7: 7.7113549 | AI7: 5.1313148 | AJ7: 10.943736 | AK7: 7.1807483
A8: 5 | B8: DEQ.DE | C8: Deutsche EuroShop AG | D8: Real Estate | E8: Germany | F8: 1440449152 | G8: 0.7343 | H8: 0.1114 | I8: 8.01 | J8: 0.0001 | K8: 4.06 | L8: 0.0941 | N8: 140000 | O8: 15.22 | P8: 2024 | Q8: 271403000 | R8: 199291000 | S8: 199151000 | T8: 123514000 | U8: 4364405000 | V8: 1809108000 | W8: 212438000 | X8: 1596670000 | Y8: 15000 | Z8: 46083 | AA8: 20.55 | AB8: 75023389 | AC8: 17.1794 | AD8: 24.8651 | AE8: 4.3388 | AF8: -3.7689 | AG8: 17.17941 | AH8: 24.865123 | AI8: 4.338843 | AJ8: 15.632954 | AK8: 7.2278686
A9: 92 | B9: ACS.MC | C9: ACS, Actividades de Construcción y Servicios, S.A. | D9: Industrials | E9: Spain | F9: 27067064320 | G9: 0.0706 | H9: 0.0856 | I9: 0.52 | J9: 0.0159 | L9: 0.1418 | N9: 969658000 | O9: 14.14 | P9: 2024 | Q9: 41633120000 | R9: 2702859000 | S9: 1836656000 | T9: 827580000 | U9: 42025282000 | V9: 14204703000 | W9: 11413659000 | X9: 2791044000 | Y9: 612491000 | Z9: 46085 | AA9: 103.7 | AB9: 260510722 | AC9: 15.9284 | AD9: 3.2945 | AE9: 13.6114 | AF9: -0.1074 | AG9: 15.928387 | AH9: 3.2945359 | AI9: 13.611411 | AJ9: 11.443139 | AK9: 10.014235
A10: 6 | B10: AMP.MI | C10: Amplifon S.p.A. | D10: Healthcare | E10: Italy | F10: 2711829248 | G10: 0.2313 | H10: 0.1124 | I10: 2.57 | J10: 0.0608 | K10: 9.65 | L10: 0.0734 | N10: 302718000 | O10: 13.38 | P10: 2024 | Q10: 2409241000 | R10: 557254000 | S10: 254536000 | T10: 145374000 | U10: 3992762000 | V10: 1721518000 | W10: 288834000 | X10: 1432684000 | Y10: 146421000 | Z10: 46083 | AA10: 12.845 | AB10: 219937482 | AC10: 17.2279 | AD10: 8.5174 | AE10: 7.2063 | AF10: -1.1071 | AG10: 17.2279 | AH10: 8.5173675 | AI10: 7.2062708 | AJ10: 11.608251 | AK10: 4.866415
A11: 11 | B11: DIA.MI | C11: DiaSorin S.p.A. | D11: Healthcare | E11: Italy | F11: 3673987072 | G11: 0.3366 | H11: 0.0651 | I11: 1.68 | J11: 0.101 | K11: 14.48 | L11: -0.0081 | N11: 129041000 | O11: 11.34 | P11: 2024 | Q11: 1185427000 | R11: 399044000 | S11: 270003000 | T11: 188105000 | U11: 3304920000 | V11: 1014189000 | W11: 344270000 | X11: 669919000 | Y11: 119716000 | Z11: 46083 | AA11: 70.44 | AB11: 52679895 | AC11: 14.9344 | AD11: 11.9397 | AE11: 8.7834 | AF11: -0.5129 | AG11: 14.934358 | AH11: 11.939671 | AI11: 8.783423 | AJ11: 12.190671 | AK11: 9.2069723
A12: 7 | B12: IRE.MI | C12: Iren SpA | D12: Utilities | E12: Italy | F12: 3382187520 | G12: 0.2076 | H12: 0.0748 | I12: 0.23 | J12: 0.1396 | K12: 8.57 | L12: 0.1133 | N12: 655475000 | O12: 6.62 | P12: 2024 | Q12: 5949243000 | R12: 1234819000 | S12: 579344000 | T12: 268471000 | U12: 12211318000 | V12: 614151000 | W12: 326568000 | X12: 287583000 | Y12: 830217000 | Z12: 46083 | AA12: 2.81 | AB12: 1283075732 | AC12: 15.4047 | AD12: 7.7471 | AE12: 16.2413 | AF12: 0.2158 | AG12: 15.404703 | AH12: 7.7471054 | AI12: 16.241291 | AJ12: 13.3584 | AK12: 2.7390148
A13: 35 | B13: ADV.DE | C13: Adtran Networks SE | D13: Technology | E13: Germany | F13: 1166020736 | G13: 0.0957 | H13: 0.0005 | I13: 1.77 | J13: 0.1427 | K13: 8.21 | L13: -0.0813 | N13: 83698000 | O13: 142.25 | P13: 2024 | Q13: 438085000 | R13: 41926000 | S13: -41772000 | T13: -62701000 | U13: 670003000 | V13: 97220000 | W13: 23049000 | X13: 74171000 | Y13: 62495000 | Z13: 46083 | AA13: 22.3 | AB13: 52054500 | AC13: 11.802 | AD13: 4.1103 | AE13: 8.5779 | AF13: -0.9465 | AG13: 11.801952 | AH13: 4.1102986 | AI13: 8.5778744 | AJ13: 8.5272326 | AK13: 27.8114
A14: 8 | B14: JUVE.MI | C14: Juventus Football Club S.p.A. | D14: Communication Services | E14: Italy | F14: 855298880 | G14: -0.0498 | H14: -0.24 | I14: -12.41 | J14: 0.405 | K14: -0.81 | L14: -0.0514 | N14: 152391000 | O14: 18.76 | P14: 2024 | Q14: 393112000 | R14: -19570000 | S14: -171961000 | T14: -199229000 | U14: 678980000 | V14: 279263000 | W14: 36424000 | X14: 242839000 | Y14: 159206000 | Z14: 46083 | AA14: 2.292 | AB14: 379121815 | AC14: 1 | AD14: 1 | AE14: 1 | AF14: 7.0502 | AG14: 1 | AH14: 1 | AI14: 1 | AJ14: 1 | AK14: -43.704593
A15: 9 | B15: BME.L | C15: B&M European Value Retail S.A. | D15: Consumer Defensive | E15: Luxembourg | F15: 1865753088 | G15: 0.1515 | H15: 0.2905 | I15: 2.78 | J15: 0.0239 | K15: 6.03 | L15: 0.0609 | N15: 273000000 | O15: 7.15 | P15: 2024 | Q15: 5484000000 | R15: 872000000 | S15: 614000000 | T15: 367000000 | U15: 3625000000 | V15: 2267000000 | W15: 182000000 | X15: 2085000000 | Y15: 126000000 | Z15: 46083 | AA15: 189.04 | AB15: 1005038256 | AC15: 25 | AD15: 5.9238 | AE15: 6.9424 | AF15: -1.0795 | AG15: 25 | AH15: 5.9238269 | AI15: 6.9424276 | AJ15: 13.859876 | AK15: 2.1396251
A16: 99 | B16: AENA.MC | C16: Aena S.M.E., S.A. | D16: Industrials | E16: Spain | F16: 37874999296 | G16: 0.6208 | H16: 0.0456 | I16: 0.81 | J16: 0.1423 | L16: 0.1453 | N16: 796897000 | O16: 11.8 | P16: 2024 | Q16: 5763531000 | R16: 3649239000 | S16: 2801428000 | T16: 1934224000 | U16: 16975364000 | V16: 7011662000 | W16: 1821283000 | X16: 5190379000 | Y16: 825184000 | Z16: 46085 | AA16: 25.26 | AB16: 1500000000 | AC16: 13.9888 | AD16: 21.1763 | AE16: 11.8243 | AF16: 0.3228 | AG16: 13.988817 | AH16: 21.176315 | AI16: 11.824255 | AJ16: 15.495698 | AK16: 10.378876
A17: 10 | B17: ASHM.L | C17: Ashmore Group Plc | D17: Financial Services | E17: United Kingdom | F17: 1453789312 | G17: 0.7756 | H17: 0.0333 | I17: -3.07 | J17: 0.0014 | K17: 373.33 | L17: -0.1661 | N17: 3100000 | O17: 22.86 | P17: 2024 | Q17: 189000000 | R17: 131500000 | S17: 128400000 | T17: 93700000 | U17: 979700000 | V17: 6400000 | W17: 511800000 | X17: -505400000 | Y17: 800000 | Z17: 46083 | AA17: 231.4 | AB17: 650149952 | AC17: 13.3924 | AD17: 25 | AE17: 1 | AF17: 2.8193 | AG17: 13.392399 | AH17: 25 | AI17: 1 | AJ17: 13.15696 | AK17: 11.055432
A18: 32 | B18: TEP.PA | C18: Teleperformance SE | D18: Industrials | E18: France | F18: 3191384576 | G18: 0.1856 | H18: 0.4995 | I18: 2.02 | J18: 0.0213 | K18: 7.34 | L18: 0.0828 | N18: 739000000 | O18: 4.44 | P18: 2024 | Q18: 10280000000 | R18: 1908000000 | S18: 1129000000 | T18: 523000000 | U18: 12074000000 | V18: 4907000000 | W18: 1058000000 | X18: 3849000000 | Y18: 219000000 | Z18: 46083 | AA18: 49.6 | AB18: 58130862 | AC18: 25 | AD18: 7.0321 | AE18: 8.0712 | AF18: -0.29 | AG18: 25 | AH18: 7.0320943 | AI18: 8.0711872 | AJ18: 14.530984 | AK18: 1.6726334
A19: 43 | B19: AFX.DE | C19: Carl Zeiss Meditec AG | D19: Healthcare | E19: Germany | F19: 2232169984 | G19: 0.1557 | H19: 0.0597 | I19: 0.3 | J19: 0.0344 | K19: 13.03 | L19: 0.055 | N19: 126378000 | O19: 10.42 | P19: 2024 | Q19: 2066127000 | R19: 403061000 | S19: 270290000 | T19: 178726000 | U19: 3393200000 | V19: 151347000 | W19: 20285000 | X19: 131062000 | Y19: 152204000 | Z19: 46083 | AA19: 26.58 | AB19: 87536079 | AC19: 14.6725 | AD19: 6.0603 | AE19: 15.4991 | AF19: 0.0904 | AG19: 14.672516 | AH19: 6.0603291 | AI19: 15.499065 | AJ19: 12.336825 | AK19: 5.5380451
A20: 12 | B20: GNS.L | C20: Genus plc | D20: Healthcare | E20: United Kingdom | F20: 1823043072 | G20: 0.1393 | H20: 0.0267 | I20: 2.33 | J20: 0.0276 | K20: 4.57 | L20: 0.046 | N20: 44700000 | O20: 21.52 | P20: 2024 | Q20: 668800000 | R20: 73700000 | S20: 26800000 | T20: 7900000 | U20: 987800000 | V20: 291200000 | W20: 42500000 | X20: 248700000 | Y20: 24700000 | Z20: 46083 | AA20: 2870 | AB20: 66413228 | AC20: 13.0724 | AD20: 5.5273 | AE20: 7.5486 | AF20: -1.1935 | AG20: 13.07237 | AH20: 5.5273207 | AI20: 7.5485539 | AJ20: 9.1517105 | AK20: 24.735998
A21: 31 | B21: IMCD.AS | C21: IMCD N.V. | D21: Basic Materials | E21: Netherlands | F21: 4417032704 | G21: 0.1127 | H21: 0.0684 | I21: 2.72 | J21: 0.0056 | K21: 8.12 | L21: 0.0135 | N21: 142918000 | O21: 11.2 | P21: 2024 | Q21: 4727602000 | R21: 606812000 | S21: 452528000 | T21: 278243000 | U21: 4878261000 | V21: 1695652000 | W21: 522780000 | X21: 1172872000 | Y21: 26452000 | Z21: 46083 | AA21: 79.22 | AB21: 59032832 | AC21: 15.0944 | AD21: 4.6628 | AE21: 7.0148 | AF21: -1.401 | AG21: 15.094372 | AH21: 4.6628072 | AI21: 7.0147717 | AJ21: 9.5410226 | AK21: 7.2790794
A22: 13 | B22: COFB.BR | C22: Cofinimmo SA | D22: Real Estate | E22: Belgium | F22: 3206888960 | G22: 0.7352 | H22: 0.0869 | I22: 10.02 | J22: 0.0012 | K22: 6.81 | L22: -0.0136 | N22: 1856000 | O22: 23.43 | Z22: 46083 | AA22: 91.45 | AB22: 38086569 | AC22: 15.9914 | AD22: 24.8944 | AE22: 3.9956 | AF22: -5.0081 | AG22: 15.991423 | AH22: 24.894373 | AI22: 3.9956201 | AJ22: 15.063567
A23: 14 | B23: VOS.DE | C23: Vossloh AG | D23: Industrials | E23: Germany | F23: 1497346304 | G23: 0.1361 | H23: 0.0539 | I23: 0.96 | J23: 0.046 | K23: 8.76 | L23: 0.0888 | N23: 55200000 | O23: 12.97 | P23: 2024 | Q23: 1209600000 | R23: 164600000 | S23: 109400000 | T23: 69200000 | U23: 1490800000 | V23: 253500000 | W23: 94700000 | X23: 158800000 | Y23: 55700000 | Z23: 46083 | AA23: 80.2 | AB23: 19320597 | AC23: 14.3913 | AD23: 5.4233 | AE23: 11.1074 | AF23: -0.3372 | AG23: 14.391278 | AH23: 5.4233191 | AI23: 11.107381 | AJ23: 10.715721 | AK23: 9.0968791
A24: 160 | B24: ALFA.ST | C24: Alfa Laval AB (publ) | D24: Industrials | E24: Sweden | F24: 212945715200 | G24: 0.2024 | H24: 0.0306 | I24: 0.98 | J24: 0.0382 | L24: 0.1044 | N24: 2503000000 | O24: 16.05 | P24: 2024 | Q24: 66954000000 | R24: 12738000000 | S24: 10320000000 | T24: 7391000000 | U24: 88803000000 | V24: 13592000000 | W24: 7369000000 | X24: 6223000000 | Y24: 3336000000 | Z24: 46085 | AA24: 515.8 | AB24: 413326315 | AC24: 13.2615 | AD24: 7.5781 | AE24: 11.02 | AF24: -0.3023 | AG24: 13.261478 | AH24: 7.5781028 | AI24: 11.020004 | AJ24: 10.884023 | AK24: 16.717359
A25: 15 | B25: JDW.L | C25: J D Wetherspoon plc | D25: Consumer Cyclical | E25: United Kingdom | F25: 715177344 | G25: 0.1131 | H25: 0.0871 | I25: 4.69 | J25: 0.0542 | K25: 3.42 | L25: 0.4721 | N25: 102382000 | O25: 8.89 | P25: 2024 | Q25: 2035500000 | R25: 230222000 | S25: 127840000 | T25: 48785000 | U25: 1904370000 | V25: 1137376000 | W25: 57233000 | X25: 1080143000 | Y25: 110266000 | Z25: 46083 | AA25: 706.5 | AB25: 105405650 | AC25: 16.0011 | AD25: 4.6758 | AE25: 5.4368 | AF25: -2.5563 | AG25: 16.001121 | AH25: 4.6758074 | AI25: 5.4368058 | AJ25: 9.4342325 | AK25: 3.1064683
A26: 16 | B26: SBT.PA | C26: Oeneo SA | D26: Consumer Defensive | E26: France | F26: 597083584 | G26: 0.2115 | H26: 0.0636 | I26: 0.88 | J26: 0.0494 | K26: 12.08 | L26: -0.0186 | N26: 20371000 | O26: 11.16 | P26: 2024 | Q26: 305728000 | R26: 63293000 | S26: 42048000 | T26: 28850000 | U26: 501741000 | V26: 104608000 | W26: 40370000 | X26: 64238000 | Y26: 21536000 | Z26: 46083 | AA26: 9.24 | AB26: 64340909 | AC26: 14.8616 | AD26: 7.8739 | AE26: 11.4755 | AF26: -0.1852 | AG26: 14.861624 | AH26: 7.8738574 | AI26: 11.475478 | AJ26: 11.74945 | AK26: 9.4336433
A27: 105 | B27: ANA.MC | C27: Acciona, S.A. | D27: Industrials | E27: Spain | F27: 12034308096 | G27: 0.1335 | H27: -0.0409 | I27: 3.25 | J27: 0.1423 | L27: 0.2341 | N27: 1372000000 | O27: 7.32 | P27: 2024 | Q27: 19190000000 | R27: 2562000000 | S27: 1423000000 | T27: 422000000 | U27: 34620000000 | V27: 12556000000 | W27: 4240000000 | X27: 8316000000 | Y27: 2731000000 | Z27: 46085 | AA27: 220.4 | AB27: 54503208 | AC27: 9.7945 | AD27: 5.3388 | AE27: 6.4464 | AF27: -1.8471 | AG27: 9.7944965 | AH27: 5.3388178 | AI27: 6.4464025 | AJ27: 7.4533647 | AK27: 4.6972319
A28: 17 | B28: GPE.L | C28: Great Portland Estates Plc | D28: Real Estate | E28: United Kingdom | F28: 1315115776 | G28: 1.4034 | H28: -0.0035 | I28: 6.93 | J28: 0.0064 | K28: 10.41 | L28: 0.0389 | N28: 1700000 | O28: 71.98 | P28: 2024 | Q28: 95400000 | R28: -288600000 | S28: -290200000 | T28: -307800000 | U28: 2478000000 | V28: 815500000 | W28: 5900000 | X28: 809600000 | Y28: 100000 | Z28: 46083 | AA28: 339 | AB28: 403409734 | AC28: 11.608 | AD28: 25 | AE28: 4.5951 | AF28: -2.4788 | AG28: 11.607995 | AH28: 25 | AI28: 4.5951216 | AJ28: 13.521734 | AK28: -4.5568807
A29: 44 | B29: IWG.L | C29: International Workplace Group plc | D29: Real Estate | E29: Switzerland | F29: 2029408768 | G29: 0.4976 | H29: 0.5381 | I29: 3.74 | J29: 0.0642 | K29: 4.18 | L29: 0.073 | N29: 1344000000 | O29: 19.61 | P29: 2024 | Q29: 3690000000 | R29: 1836000000 | S29: 492000000 | T29: 20000000 | U29: 9633000000 | V29: 6995000000 | W29: 137000000 | X29: 6858000000 | Y29: 237000000 | Z29: 46083 | AA29: 212.4 | AB29: 988797019 | AC29: 25 | AD29: 17.1723 | AE29: 6.034 | AF29: -0.8935 | AG29: 25 | AH29: 17.172253 | AI29: 6.0340055 | AJ29: 16.961877 | AK29: 1.1053425
A30: 18 | B30: VIRP.PA | C30: Virbac SA | D30: Healthcare | E30: France | F30: 2894538240 | G30: 0.1977 | H30: 0.0428 | I30: 0.57 | J30: 0.0576 | K30: 24.85 | L30: 0.0963 | N30: 57352000 | O30: 11.87 | P30: 2024 | Q30: 1397379000 | R30: 276264000 | S30: 218912000 | T30: 145290000 | U30: 1848522000 | V30: 307014000 | W30: 149631000 | X30: 157383000 | Y30: 80439000 | Z30: 46083 | AA30: 362 | AB30: 8377824 | AC30: 13.853 | AD30: 7.4254 | AE30: 13.2562 | AF30: -0.0448 | AG30: 13.853047 | AH30: 7.4253504 | AI30: 13.256178 | AJ30: 11.745677 | AK30: 10.477435
A31: 96 | B31: ARGX.BR | C31: argenx SE | D31: Healthcare | E31: Netherlands | F31: 40100450304 | G31: 0.048 | H31: -0.0038 | I31: -13.89 | J31: 0.0312 | L31: 0.8659 | N31: 17527000 | O31: 32.34 | P31: 2024 | Q31: 2190231000 | R31: 105171000 | S31: 87644000 | T31: 833040000 | U31: 6202522000 | V31: 39053000 | W31: 1499936000 | X31: -1460883000 | Y31: 68301000 | Z31: 46085 | AA31: 648.2 | AB31: 61883406 | AC31: 11.5934 | AD31: 2.56 | AE31: 1.1418 | AF31: 8.3863 | AG31: 11.593448 | AH31: 2.5600244 | AI31: 1.1417667 | AJ31: 5.7479165 | AK31: 381.2881
A32: 19 | B32: BSLN.SW | C32: Basilea Pharmaceutica AG | D32: Healthcare | E32: Switzerland | F32: 646716672 | G32: 0.2197 | H32: 0.0916 | I32: -1.38 | J32: 0.0123 | K32: 15.21 | L32: 0.168 | N32: 1814000 | O32: 10.88 | P32: 2024 | Q32: 208543000 | R32: 66336000 | S32: 64604000 | T32: 77593000 | U32: 257764000 | V32: 111671000 | W32: 120700000 | X32: -9029000 | Y32: 1792000 | Z32: 46083 | AA32: 54.2 | AB32: 12271663 | AC32: 16.2193 | AD32: 8.1404 | AE32: 1 | AF32: 1.2199 | AG32: 16.219323 | AH32: 8.1403616 | AI32: 1 | AJ32: 9.2298377 | AK32: 9.7491056
A33: 20 | B33: TRE.MC | C33: Técnicas Reunidas, S.A. | D33: Industrials | E33: Spain | F33: 2250756096 | G33: 0.0491 | H33: 0.0337 | I33: -0.59 | J33: 0.0016 | K33: 5.48 | L33: 0.1686 | N33: 9362000 | O33: 7.89 | P33: 2024 | Q33: 4451446000 | R33: 218784000 | S33: 185875000 | T33: 89942000 | U33: 4629235000 | V33: 888637000 | W33: 1018409000 | X33: -129772000 | Y33: 7256000 | Z33: 46083 | AA33: 35.3 | AB33: 78097009 | AC33: 13.4118 | AD33: 2.5958 | AE33: 25 | AF33: 0.4601 | AG33: 13.411795 | AH33: 2.5957749 | AI33: 25 | AJ33: 13.64345 | AK33: 10.287572
A34: 21 | B34: FAN.L | C34: Volution Group plc | D34: Industrials | E34: United Kingdom | F34: 1303555328 | G34: 0.2381 | H34: 0.0524 | I34: 0.82 | J34: 0.0212 | K34: 14 | L34: 0.0849 | N34: 20280000 | O34: 16.27 | P34: 2024 | Q34: 347611000 | R34: 82763000 | S34: 62483000 | T34: 42797000 | U34: 430315000 | V34: 85993000 | W34: 18243000 | X34: 67750000 | Y34: 7382000 | Z34: 46083 | AA34: 691 | AB34: 198410249 | AC34: 14.3185 | AD34: 8.7384 | AE34: 11.7728 | AF34: -0.1329 | AG34: 14.318544 | AH34: 8.7383709 | AI34: 11.772787 | AJ34: 11.880765 | AK34: 15.75046
A35: 22 | B35: BOSS.DE | C35: Hugo Boss AG | D35: Consumer Cyclical | E35: Germany | F35: 2419016704 | G35: 0.1792 | H35: 0.206 | I35: 1.34 | J35: 0.0667 | K35: 13.73 | L35: 0.1621 | N35: 414206000 | O35: 11.63 | P35: 2024 | Q35: 4307349000 | R35: 771940000 | S35: 357734000 | T35: 213468000 | U35: 3782421000 | V35: 1248211000 | W35: 210622000 | X35: 1037589000 | Y35: 287190000 | Z35: 46083 | AA35: 36.22 | AB35: 69016167 | AC35: 21.7665 | AD35: 6.8241 | AE35: 9.7026 | AF35: -0.3006 | AG35: 21.766494 | AH35: 6.824091 | AI35: 9.7026333 | AJ35: 13.664615 | AK35: 3.1336849
A36: 27 | B36: ATO.PA | C36: Atos SE | D36: Technology | E36: France | F36: 741217216 | G36: 0.147 | H36: -2.4905 | I36: 0.76 | J36: 0.0464 | K36: 3.72 | L36: -0.0386 | N36: 568000000 | O36: 15.61 | P36: 2024 | Q36: 9577000000 | R36: 1408000000 | S36: 840000000 | T36: 248000000 | U36: 8246000000 | V36: 2811000000 | W36: 1739000000 | X36: 1072000000 | Y36: 444000000 | Z36: 46083 | AA36: 39.2825 | AB36: 19378227 | AC36: 1 | AD36: 5.7776 | AE36: 12.0904 | AF36: -3.7663 | AG36: 1 | AH36: 5.7775746 | AI36: 12.090368 | AJ36: 5.7603828 | AK36: 0.52643268
A37: 23 | B37: SMHN.DE | C37: SUSS MicroTec SE | D37: Technology | E37: Germany | F37: 1029371776 | G37: 0.193 | H37: 0.0252 | I37: -1.43 | J37: 0.017 | K37: 218.51 | L37: 0.2078 | N37: 7821000 | O37: 10.13 | P37: 2024 | Q37: 446147000 | R37: 86094000 | S37: 78273000 | T37: 110343000 | U37: 500873000 | V37: 13295000 | W37: 136239000 | X37: -122944000 | Y37: 7564000 | Z37: 46083 | AA37: 53.25 | AB37: 19115538 | AC37: 12.9996 | AD37: 7.2726 | AE37: 1 | AF37: 1.1249 | AG37: 12.999636 | AH37: 7.272598 | AI37: 1 | AJ37: 7.6816339 | AK37: 11.956371
A38: 24 | B38: TRN.L | C38: Trainline plc | D38: Consumer Cyclical | E38: United Kingdom | F38: 715123648 | G38: 0.2989 | H38: 0.1341 | I38: 0.62 | J38: 0.0957 | K38: 16.3 | L38: 0.3541 | N38: 43167000 | O38: 7.23 | P38: 2024 | Q38: 396718000 | R38: 98147000 | S38: 56485000 | T38: 33986000 | U38: 681933000 | V38: 153113000 | W38: 91085000 | X38: 62028000 | Y38: 39883000 | Z38: 46083 | AA38: 189.9 | AB38: 375519674 | AC38: 18.2801 | AD38: 10.7144 | AE38: 12.9229 | AF38: 0.1744 | AG38: 18.280116 | AH38: 10.714402 | AI38: 12.922873 | AJ38: 14.403229 | AK38: 7.2862507
A39: 112 | B39: BAB.L | C39: Babcock International Group PLC | D39: Industrials | E39: United Kingdom | F39: 6874880512 | G39: 0.1032 | H39: 0.0263 | I39: 0.76 | J39: 0.0266 | L39: 0.0572 | N39: 117700000 | O39: 14.75 | Z39: 46085 | AA39: 1380 | AB39: 498172502 | AC39: 13.053 | AD39: 4.3541 | AE39: 12.0904 | AF39: -0.2953 | AG39: 13.052975 | AH39: 4.3540524 | AI39: 12.090368 | AJ39: 10.154516
A40: 25 | B40: PROX.BR | C40: Proximus PLC | D40: Communication Services | E40: Belgium | F40: 2392254720 | G40: 0.3066 | H40: 0.0535 | I40: 2.2 | J40: 0.2312 | K40: 10.68 | L40: 0.0226 | N40: 1601000000 | O40: 2.96 | P40: 2024 | Q40: 6376000000 | R40: 1955000000 | S40: 696000000 | T40: 447000000 | U40: 13327000000 | V40: 4801000000 | W40: 497000000 | X40: 4304000000 | Y40: 1474000000 | Z40: 46083 | AA40: 7.295 | AB40: 322461674 | AC40: 14.3719 | AD40: 10.9647 | AE40: 7.7554 | AF40: -0.8772 | AG40: 14.371882 | AH40: 10.964656 | AI40: 7.7553945 | AJ40: 11.364768 | AK40: 1.2236597
A41: 51 | B41: WCH.DE | C41: Wacker Chemie AG | D41: Basic Materials | E41: Germany | F41: 3625971712 | G41: 0.1411 | H41: -0.0941 | I41: 1.09 | J41: 0.1139 | K41: 10.61 | L41: -0.0013 | N41: 472700000 | O41: 8.53 | P41: 2024 | Q41: 5721800000 | R41: 807200000 | S41: 334500000 | T41: 241000000 | U41: 9409900000 | V41: 1925200000 | W41: 1046700000 | X41: 878500000 | Y41: 651600000 | Z41: 46083 | AA41: 78.1 | AB41: 51762620 | AC41: 7.2149 | AD41: 5.5858 | AE41: 10.5693 | AF41: -0.6164 | AG41: 7.214868 | AH41: 5.5858217 | AI41: 10.569325 | AJ41: 7.7324911 | AK41: 4.4920363
A42: 26 | B42: PSM.DE | C42: ProSiebenSat.1 Media SE | D42: Communication Services | E42: Germany | F42: 1006776192 | G42: 0.0397 | H42: 0.0924 | I42: 12.28 | J42: 0.2977 | K42: 1.7 | L42: -0.0742 | N42: 227000000 | O42: 7.47 | Z42: 46083 | AA42: 4.624 | AB42: 226700343 | AC42: 16.2581 | AD42: 2.2903 | AE42: 3.7338 | AF42: -7.191 | AG42: 16.258114 | AH42: 2.2902702 | AI42: 3.7337925 | AJ42: 8.3104646
A43: 147 | B43: BAMI.MI | C43: Banco BPM S.p.A. | D43: Financial Services | E43: Italy | F43: 17303830528 | G43: 0 | H43: -0.2974 | I43: 0 | J43: 0.0376 | L43: 0.1618 | N43: 292203000 | O43: 0 | P43: 2024 | Q43: 6826516000 | R43: 0 | S43: 0 | T43: 1920393000 | U43: 198209087000 | V43: 29389813000 | W43: 13808915000 | X43: 15580898000 | Y43: 256434000 | Z43: 46085 | AA43: 11.505 | AB43: 1503373604 | AC43: 1 | AD43: 1 | AE43: 19.4117 | AF43: -0.4164 | AG43: 1 | AH43: 1 | AI43: 19.411657 | AJ43: 6.523497 | AK43: #NUM!
A44: 47 | B44: WAF.DE | C44: Siltronic AG | D44: Technology | E44: Germany | F44: 1575000064 | G44: 0.2665 | H44: -0.2257 | I44: 3.26 | J44: 0.4954 | K44: 9.99 | L44: 0.0188 | N44: 238500000 | O44: 9.19 | P44: 2024 | Q44: 1412800000 | R44: 376500000 | S44: 138000000 | T44: 63000000 | U44: 5084400000 | V44: 1523300000 | W44: 297100000 | X44: 1226200000 | Y44: 699900000 | Z44: 46083 | AA44: 55.5 | AB44: 30000000 | AC44: 1 | AD44: 9.6614 | AE44: 6.437 | AF44: -1.9522 | AG44: 1 | AH44: 9.6613853 | AI44: 6.4370379 | AJ44: 5.229527 | AK44: 4.1832671
A45: 28 | B45: RMV.L | C45: Rightmove plc | D45: Communication Services | E45: United Kingdom | F45: 3314097920 | G45: 0.6785 | H45: 0.061 | I45: -0.11 | J45: 0.0233 | K45: 1763.66 | L45: 0.0855 | N45: 5999000 | O45: 11.15 | P45: 2024 | Q45: 389882000 | R45: 264549000 | S45: 258550000 | T45: 192713000 | U45: 118498000 | V45: 6162000 | W45: 35661000 | X45: -29499000 | Y45: 9078000 | Z45: 46083 | AA45: 441 | AB45: 759417456 | AC45: 14.7356 | AD45: 23.0516 | AE45: 21.5072 | AF45: 0.9656 | AG45: 14.735552 | AH45: 23.051595 | AI45: 21.507164 | AJ45: 19.261848 | AK45: 12.52735
A46: 53 | B46: BEN.PA | C46: Bénéteau S.A. | D46: Consumer Cyclical | E46: France | F46: 571827584 | G46: 0.1213 | H46: 0.1805 | I46: -0.35 | J46: 0.0625 | K46: 20.12 | L46: -0.0345 | N46: 56869000 | O46: 7.59 | P46: 2024 | Q46: 1034380000 | R46: 125461000 | S46: 63627000 | T46: 92851000 | U46: 1652310000 | V46: 411943000 | W46: 455962000 | X46: -44019000 | Y46: 64643000 | Z46: 46083 | AA46: 7.81 | AB46: 80122731 | AC46: 20.53 | AD46: 4.9423 | AE46: 25 | AF46: 0.6083 | AG46: 20.530018 | AH46: 4.9423116 | AI46: 25 | AJ46: 17.194701 | AK46: 4.5578115
A47: 29 | B47: MEL.MC | C47: Meliá Hotels International, S.A. | D47: Consumer Cyclical | E47: Spain | F47: 1686660352 | G47: 0.2835 | H47: 0.2005 | I47: 3.99 | J47: 0.0395 | K47: 5.57 | L47: 0.0903 | N47: 260103000 | O47: 11.47 | P47: 2024 | Q47: 2005385000 | R47: 568586000 | S47: 326463000 | T47: 140626000 | U47: 4581787000 | V47: 2440937000 | W47: 171272000 | X47: 2269665000 | Y47: 79215000 | Z47: 46083 | AA47: 7.885 | AB47: 220190651 | AC47: 21.4998 | AD47: 10.2139 | AE47: 5.8548 | AF47: -1.7731 | AG47: 21.499803 | AH47: 10.213894 | AI47: 5.8548015 | AJ47: 13.42053 | AK47: 2.966412
A48: 30 | B48: SOLB.BR | C48: Solvay SA | D48: Basic Materials | E48: Belgium | F48: 2713404928 | G48: 0.1445 | H48: 0.1703 | I48: 2.38 | J48: 0.0464 | K48: 5.49 | L48: -0.1561 | N48: 404000000 | O48: 5.58 | P48: 2024 | Q48: 5130000000 | R48: 805000000 | S48: 443000000 | T48: 223000000 | U48: 6694000000 | V48: 1881000000 | W48: 539000000 | X48: 1342000000 | Y48: 285000000 | Z48: 46083 | AA48: 26.72 | AB48: 104465072 | AC48: 20.0354 | AD48: 5.6963 | AE48: 7.4732 | AF48: -1.0162 | AG48: 20.035427 | AH48: 5.6963234 | AI48: 7.4732364 | AJ48: 11.965039 | AK48: 3.3706894
A49: 141 | B49: BESI.AS | C49: BE Semiconductor Industries N.V. | D49: Technology | E49: Netherlands | F49: 14430826496 | G49: 0.3497 | H49: 0.0094 | I49: 0.7 | J49: 0.0707 | L49: -0.0588 | N49: 33723000 | O49: 69.11 | P49: 2024 | Q49: 607473000 | R49: 224192000 | S49: 195591000 | T49: 181992000 | U49: 1234476000 | V49: 544709000 | W49: 342319000 | X49: 202390000 | Y49: 31476000 | Z49: 46085 | AA49: 183.2 | AB49: 78792393 | AC49: 12.2335 | AD49: 12.3654 | AE49: 12.4304 | AF49: 0.0128 | AG49: 12.233506 | AH49: 12.365428 | AI49: 12.430366 | AJ49: 12.33214 | AK49: 64.36816
A50: 80 | B50: BKT.MC | C50: Bankinter, S.A. | D50: Financial Services | E50: Spain | F50: 11781907456 | G50: 0 | H50: 0.152 | I50: 0 | J50: 0.0489 | L50: 0.116 | N50: 87453000 | O50: 0 | Z50: 46085 | AA50: 13.1 | AB50: 898696272 | AC50: 19.1481 | AD50: 1 | AE50: 19.4117 | AF50: 0.2128 | AG50: 19.148074 | AH50: 1 | AI50: 19.411657 | AJ50: 13.782727
A51: 33 | B51: COL.MC | C51: Colonial SFL, Socimi S. A. | D51: Real Estate | E51: Spain | F51: 3197181184 | G51: 0.9453 | H51: 0.112 | I51: 9.39 | J51: 0.0084 | K51: 4.24 | L51: 0.0604 | N51: 6207000 | O51: 28.28 | P51: 2024 | Q51: 502412000 | R51: 474924000 | S51: 467592000 | T51: 307395000 | U51: 12236502000 | V51: 4999588000 | W51: 541256000 | X51: 4458332000 | Y51: 4235000 | Z51: 46083 | AA51: 5.55 | AB51: 613655183 | AC51: 17.2085 | AD51: 25 | AE51: 4.0889 | AF51: -4.3428 | AG51: 17.208504 | AH51: 25 | AI51: 4.088909 | AJ51: 15.610074 | AK51: 6.7319849
A52: 34 | B52: TFI.PA | C52: TF1 SA | D52: Communication Services | E52: France | F52: 1497814272 | G52: 0.2924 | H52: 0.0656 | I52: -0.69 | J52: 0.156 | K52: 55.05 | L52: -0.0278 | N52: 423500000 | O52: 3.67 | P52: 2024 | Q52: 2356100000 | R52: 716400000 | S52: 291600000 | T52: 205500000 | U52: 3884200000 | V52: 271000000 | W52: 708300000 | X52: -437300000 | Y52: 321300000 | Z52: 46083 | AA52: 7.23 | AB52: 210367171 | AC52: 14.9586 | AD52: 10.5031 | AE52: 25 | AF52: 0.8567 | AG52: 14.958602 | AH52: 10.503148 | AI52: 25 | AJ52: 16.634385 | AK52: 2.0907514
A53: 58 | B53: DKSH.SW | C53: DKSH Holding AG | D53: Industrials | E53: Switzerland | F53: 3847098112 | G53: 0.0402 | H53: 0.0733 | I53: 0.48 | J53: 0.0035 | K53: 16.24 | L53: -0.0073 | N53: 121700000 | O53: 10.76 | P53: 2024 | Q53: 11093600000 | R53: 472000000 | S53: 345400000 | T53: 214800000 | U53: 5848300000 | V53: 839800000 | W53: 609100000 | X53: 230700000 | Y53: 41600000 | Z53: 46083 | AA53: 60.3 | AB53: 64984764 | AC53: 15.332 | AD53: 2.3065 | AE53: 13.9129 | AF53: -0.1371 | AG53: 15.33197 | AH53: 2.3065204 | AI53: 13.912879 | AJ53: 10.998608 | AK53: 8.1506316
A54: 125 | B54: BNR.DE | C54: Brenntag SE | D54: Basic Materials | E54: Germany | F54: 6992583680 | G54: 0.082 | H54: 0.0807 | I54: 1.96 | J54: 0.0211 | L54: 0.0607 | N54: 444100000 | O54: 9.85 | P54: 2024 | Q54: 16237400000 | R54: 1332100000 | S54: 888000000 | T54: 536200000 | U54: 11668000000 | V54: 3375900000 | W54: 763300000 | X54: 2612600000 | Y54: 342200000 | Z54: 46085 | AA54: 48.43 | AB54: 144385372 | AC54: 15.6908 | AD54: 3.665 | AE54: 8.185 | AF54: -0.9646 | AG54: 15.69079 | AH54: 3.6650416 | AI54: 8.1849864 | AJ54: 9.8313244 | AK54: 5.2492934
A55: 36 | B55: SCYR.MC | C55: Sacyr, S.A. | D55: Industrials | E55: Spain | F55: 3275656448 | G55: 0.2793 | H55: 0.3369 | I55: 5.62 | J55: 0.0728 | K55: 1.79 | L55: -0.0209 | N55: 184480000 | O55: 0 | P55: 2024 | Q55: 4571004000 | R55: 1341614000 | S55: 1178775000 | T55: 113373000 | U55: 17968421000 | V55: 10342908000 | W55: 1726932000 | X55: 8615976000 | Y55: 332546000 | Z55: 46080 | AA55: 4.536 | AB55: 799649302 | AC55: 25 | AD55: 10.0774 | AE55: 5.0182 | AF55: -2.5652 | AG55: 25 | AH55: 10.077392 | AI55: 5.0182057 | AJ55: 14.528679 | AK55: 2.4415789
A56: 37 | B56: DOM.L | C56: Domino's Pizza Group plc | D56: Consumer Cyclical | E56: United Kingdom | F56: 721620096 | G56: 0.268 | H56: 0.1178 | I56: 2.78 | J56: 0.0278 | K56: 5.65 | L56: 0.0601 | N56: 21700000 | O56: 10.92 | P56: 2024 | Q56: 664500000 | R56: 178100000 | S56: 156400000 | T56: 90200000 | U56: 602900000 | V56: 547400000 | W56: 52200000 | X56: 495200000 | Y56: 18500000 | Z56: 46083 | AA56: 195.9 | AB56: 381607649 | AC56: 17.4897 | AD56: 9.7101 | AE56: 6.9424 | AF56: -1.1815 | AG56: 17.489741 | AH56: 9.7101361 | AI56: 6.9424276 | AJ56: 11.991666 | AK56: 4.0517692
A57: 133 | B57: BOL.PA | C57: Bolloré SE | D57: Communication Services | E57: France | F57: 13052399616 | G57: 0.117 | H57: 0.0079 | I57: -13.08 | J57: 0.0134 | L57: -0.3205 | N57: 41100000 | O57: 15.6 | P57: 2024 | Q57: 3130300000 | R57: 366300000 | S57: 243100000 | T57: 1822300000 | U57: 27669900000 | V57: 395800000 | W57: 5186700000 | X57: -4790900000 | Y57: 42100000 | Z57: 46085 | AA57: 4.67 | AB57: 2793749964 | AC57: 12.1608 | AD57: 4.8026 | AE57: 1.0536 | AF57: 7.9995 | AG57: 12.160772 | AH57: 4.8025594 | AI57: 1.0535701 | AJ57: 6.6211477 | AK57: 35.633087
A58: 38 | B58: DLN.L | C58: Derwent London Plc | D58: Real Estate | E58: United Kingdom | F58: 1893225088 | G58: 0.6963 | H58: -0.0406 | I58: 9.65 | J58: 0.6414 | K58: 4.2 | L58: 0.1916 | N58: 800000 | O58: 20.23 | P58: 2024 | Q58: 220600000 | R58: 153600000 | S58: 152600000 | T58: 115900000 | U58: 5214000000 | V58: 1498100000 | W58: 15400000 | X58: 1482700000 | Y58: 141500000 | Z58: 46083 | AA58: 1796 | AB58: 112290929 | AC58: 9.809 | AD58: 23.6301 | AE58: 4.0491 | AF58: -5.0113 | AG58: 9.8090432 | AH58: 23.630104 | AI58: 4.0490712 | AJ58: 12.22737 | AK58: 12.325684
A59: 40 | B59: OCI.AS | C59: OCI N.V. | D59: Basic Materials | E59: Netherlands | F59: 749316864 | G59: 0.0399 | H59: -0.0109 | I59: -32.11 | J59: 0.0782 | K59: 0.44 | L59: -0.3758 | N59: 107100000 | O59: 0.77 | P59: 2024 | Q59: 975100000 | R59: 38900000 | S59: -68200000 | T59: 4978800000 | U59: 4329500000 | V59: 803700000 | W59: 2052900000 | X59: -1249200000 | Y59: 76300000 | Z59: 46083 | AA59: 3.592 | AB59: 210939330 | AC59: 11.2492 | AD59: 2.2968 | AE59: 1.9121 | AF59: 19.2986 | AG59: 11.249174 | AH59: 2.2967703 | AI59: 1.9121059 | AJ59: 5.7623325 | AK59: 19.262644
A60: 39 | B60: PUM.DE | C60: PUMA SE | D60: Consumer Cyclical | E60: Germany | F60: 3189307392 | G60: 0.1109 | H60: 0.1354 | I60: 1.38 | J60: 0.0298 | K60: 7.61 | L60: 0.095 | N60: 386900000 | O60: 2752.93 | P60: 2024 | Q60: 8817200000 | R60: 977600000 | S60: 590700000 | T60: 281600000 | U60: 7140600000 | V60: 1718600000 | W60: 368200000 | X60: 1350400000 | Y60: 263000000 | Z60: 46083 | AA60: 22.63 | AB60: 147136660 | AC60: 18.3432 | AD60: 4.6043 | AE60: 9.5809 | AF60: -0.5054 | AG60: 18.343152 | AH60: 4.6043063 | AI60: 9.5808595 | AJ60: 11.592811 | AK60: 3.2623848
A61: 41 | B61: SSPG.L | C61: SSP Group plc | D61: Consumer Cyclical | E61: United Kingdom | F61: 1474566272 | G61: 0.1445 | H61: 0.3362 | I61: 3.46 | J61: 0.0677 | K61: 4.45 | L61: 0.1926 | N61: 418000000 | O61: 8.73 | P61: 2024 | Q61: 3433200000 | R61: 607500000 | S61: 234100000 | T61: 27400000 | U61: 3172900000 | V61: 1936400000 | W61: 254800000 | X61: 1681600000 | Y61: 297100000 | Z61: 46083 | AA61: 191.7 | AB61: 786096898 | AC61: 25 | AD61: 5.6963 | AE61: 6.2586 | AF61: -1.4319 | AG61: 25 | AH61: 5.6963234 | AI61: 6.258565 | AJ61: 13.586467 | AK61: 2.4272696
A62: 42 | B62: SK.PA | C62: SEB SA | D62: Consumer Cyclical | E62: France | F62: 2539962624 | G62: 0 | H62: 0.1244 | I62: 0 | J62: 0 | K62: 0 | L62: 0.0087 | N62: 294900000 | O62: 5.02 | Z62: 46083 | AA62: 49.8 | AB62: 54787804 | AC62: 17.8098 | AD62: 1 | AE62: 19.4117 | AF62: 0.1742 | AG62: 17.809771 | AH62: 1 | AI62: 19.411657 | AJ62: 13.247405
A63: 61 | B63: BVI.PA | C63: Bureau Veritas SA | D63: Industrials | E63: France | F63: 12688581632 | G63: 0.1964 | H63: 0.0678 | I63: 1.35 | J63: 0.0227 | L63: 0.0461 | N63: 299500000 | O63: 11.54 | P63: 2024 | Q63: 6240900000 | R63: 1247800000 | S63: 964100000 | T63: 569400000 | U63: 7194900000 | V63: 2873200000 | W63: 1204200000 | X63: 1669000000 | Y63: 145900000 | Z63: 46085 | AA63: 28.64 | AB63: 443656690 | AC63: 15.0653 | AD63: 7.3831 | AE63: 9.6718 | AF63: -0.4794 | AG63: 15.065279 | AH63: 7.3830997 | AI63: 9.6718012 | AJ63: 11.142582 | AK63: 10.168762
A64: 45 | B64: FNAC.PA | C64: Fnac Darty SA | D64: Consumer Cyclical | E64: France | F64: 1027506816 | G64: 0.0187 | H64: 0.3671 | I64: 8.86 | J64: 0.015 | K64: 1.87 | L64: 0.0984 | N64: 0 | O64: 0 | P64: 2024 | Q64: 8253200000 | R64: 154500000 | S64: 154500000 | T64: 35900000 | U64: 8487900000 | V64: 2431200000 | W64: 1061900000 | X64: 1369300000 | Y64: 123900000 | Z64: 46080 | AA64: 35.4 | AB64: 29107842 | AC64: 25 | AD64: 1.6078 | AE64: 4.1766 | AF64: -4.7796 | AG64: 25 | AH64: 1.6077595 | AI64: 4.1766232 | AJ64: 11.735315 | AK64: 6.6505296
A65: 140 | B65: BYG.L | C65: Big Yellow Group Plc | D65: Real Estate | E65: United Kingdom | F65: 1863362944 | G65: 1.0872 | H65: 0.0615 | I65: 1.81 | J65: 0 | L65: 0.0613 | N65: 2538000 | O65: 17.74 | P65: 2024 | Q65: 199619000 | R65: 266579000 | S65: 263981000 | T65: 239833000 | U65: 2902768000 | V65: 408415000 | W65: 9356000 | X65: 399059000 | Y65: 0 | Z65: 46085 | AA65: 954 | AB65: 195937211 | AC65: 14.7598 | AD65: 25 | AE65: 8.4907 | AF65: 0.3047 | AG65: 14.759796 | AH65: 25 | AI65: 8.4907458 | AJ65: 15.951142 | AK65: 6.989909
A66: 46 | B66: OCDO.L | C66: Ocado Group plc | D66: Consumer Defensive | E66: United Kingdom | F66: 1653213696 | G66: 0.1806 | H66: -0.0789 | I66: 4.41 | J66: 0.3288 | K66: 2.34 | L66: -0.1548 | N66: 465500000 | O66: 29.73 | P66: 2024 | Q66: 1214600000 | R66: 219400000 | S66: -246100000 | T66: -336200000 | U66: 4156500000 | V66: 1698400000 | W66: 730500000 | X66: 967900000 | Y66: 399400000 | Z66: 46083 | AA66: 205.6021 | AB66: 829077513 | AC66: 7.9519 | AD66: 6.8696 | AE66: 5.591 | AF66: -2.5397 | AG66: 7.9519047 | AH66: 6.8695917 | AI66: 5.5910238 | AJ66: 6.9189465 | AK66: 7.5351581
A67: 56 | B67: GLPG.AS | C67: Galapagos NV | D67: Healthcare | E67: Belgium | F67: 1862251264 | G67: 0.1572 | H67: -0.2159 | I67: -1.21 | J67: 0.2979 | K67: 47.56 | L67: 0.0576 | N67: 45499000 | O67: -1.98 | P67: 2024 | Q67: 275649000 | R67: 43325000 | S67: -2174000 | T67: 74082000 | U67: 4135719000 | V67: 11722000 | W67: 64239000 | X67: -52517000 | Y67: 82110000 | Z67: 46083 | AA67: 28.12 | AB67: 65897071 | AC67: 1.3089 | AD67: 6.1091 | AE67: 1 | AF67: 0.6124 | AG67: 1.3088766 | AH67: 6.1090798 | AI67: 1 | AJ67: 2.6562746 | AK67: 42.983295
A68: 116 | B68: BZU.MI | C68: Buzzi S.p.A. | D68: Basic Materials | E68: Italy | F68: 8269216768 | G68: 0.3279 | H68: 0.0586 | I68: -0.57 | J68: 0.104 | L68: 0.0797 | N68: 272339000 | O68: 6.34 | P68: 2024 | Q68: 4313037000 | R68: 1414430000 | S68: 1142091000 | T68: 942316000 | U68: 8688435000 | V68: 607565000 | W68: 1410439000 | X68: -802874000 | Y68: 448413000 | Z68: 46085 | AA68: 45.58 | AB68: 181024878 | AC68: 14.6192 | AD68: 11.6569 | AE68: 25 | AF68: 0.8175 | AG68: 14.619178 | AH68: 11.656917 | AI68: 25 | AJ68: 16.844746 | AK68: 5.8463245
A69: 48 | B69: IGG.L | C69: IG Group Holdings plc | D69: Financial Services | E69: United Kingdom | F69: 4456340992 | G69: 0.6331 | H69: 0.1091 | I69: -0.84 | J69: 0.0061 | K69: 16.65 | L69: -0.0073 | N69: 57900000 | O69: 0 | P69: 2024 | Q69: 852400000 | R69: 504700000 | S69: 428900000 | T69: 307700000 | U69: 2940900000 | V69: 323200000 | W69: 948500000 | X69: -625300000 | Y69: 17500000 | Z69: 46083 | AA69: 1280 | AB69: 335316933 | AC69: 17.0679 | AD69: 21.5761 | AE69: 25 | AF69: 1.4165 | AG69: 17.067885 | AH69: 21.576072 | AI69: 25 | AJ69: 20.799975 | AK69: 8.829683
A70: 49 | B70: WIZZ.L | C70: Wizz Air Holdings Plc | D70: Industrials | E70: Hungary | F70: 1105758976 | G70: 0.2346 | H70: 0.3799 | I70: 4.87 | J70: 0.1225 | K70: 4.95 | L70: 0.5608 | N70: 966800000 | O70: 9.45 | P70: 2024 | Q70: 5073100000 | R70: 1293100000 | S70: 537800000 | T70: 376600000 | U70: 8694900000 | V70: 6269700000 | W70: 728400000 | X70: 5541300000 | Y70: 708900000 | Z70: 46083 | AA70: 1145 | AB70: 103438631 | AC70: 25 | AD70: 8.6246 | AE70: 5.3454 | AF70: -2.1086 | AG70: 25 | AH70: 8.6246191 | AI70: 5.3454347 | AJ70: 14.191016 | AK70: 0.85512256
A71: 142 | B71: CABK.MC | C71: CaixaBank, S.A. | D71: Financial Services | E71: Spain | F71: 68091854848 | G71: 0 | H71: 0.0505 | I71: 0 | J71: 0.0579 | L71: 0.1109 | N71: 791000000 | O71: 0 | Z71: 46085 | AA71: 9.688 | AB71: 6994110489 | AC71: 14.2264 | AD71: 1 | AE71: 19.4117 | AF71: 0.0707 | AG71: 14.226415 | AH71: 1 | AI71: 19.411657 | AJ71: 11.814063
A72: 50 | B72: SDF.DE | C72: K+S Aktiengesellschaft | D72: Basic Materials | E72: Germany | F72: 2711574016 | G72: 0.1315 | H72: 0.0253 | I72: 0.37 | J72: 0.1429 | K72: 16.62 | L72: 0.1307 | N72: 559700000 | O72: 4.98 | P72: 2024 | Q72: 3653100000 | R72: 480200000 | S72: -79500000 | T72: -66800000 | U72: 9353500000 | V72: 493900000 | W72: 317600000 | X72: 176300000 | Y72: 522100000 | Z72: 46083 | AA72: 15.22 | AB72: 179100000 | AC72: 13.0045 | AD72: 5.2738 | AE72: 14.8327 | AF72: -0.0288 | AG72: 13.004485 | AH72: 5.2738168 | AI72: 14.832687 | AJ72: 11.233745 | AK72: 5.6467597
A73: 70 | B73: CFR.SW | C73: Compagnie Financière Richemont SA | D73: Consumer Cyclical | E73: Switzerland | F73: 83869679616 | G73: 0.3052 | H73: 0.0389 | I73: 0.85 | J73: 0.0551 | L73: 0.0875 | N73: 1560000000 | O73: 15.29 | P73: 2024 | Q73: 20616000000 | R73: 6520000000 | S73: 5088000000 | T73: 2362000000 | U73: 42681000000 | V73: 16365000000 | W73: 10710000000 | X73: 5655000000 | Y73: 1021000000 | Z73: 46085 | AA73: 142.7 | AB73: 534182089 | AC73: 13.6639 | AD73: 10.9192 | AE73: 11.6217 | AF73: -0.0893 | AG73: 13.663939 | AH73: 10.919155 | AI73: 11.621722 | AJ73: 12.227839 | AK73: 12.863448
A74: 115 | B74: COFA.PA | C74: COFACE SA | D74: Financial Services | E74: France | F74: 2199385856 | G74: 0 | H74: 0.0912 | I74: 0 | J74: 0.0162 | L74: 0.0184 | N74: 33849000 | O74: 11.96 | P74: 2024 | Q74: 1648842000 | R74: 0 | S74: 409231000 | T74: 261067000 | U74: 8084134000 | V74: 2390978000 | W74: 507832000 | X74: 1883146000 | Y74: 26708000 | Z74: 46085 | AA74: 14.76 | AB74: 149212066 | AC74: 16.1999 | AD74: 1 | AE74: 19.4117 | AF74: 0.1277 | AG74: 16.199927 | AH74: 1 | AI74: 19.411657 | AJ74: 12.603468 | AK74: #NUM!
A75: 54 | B75: RAND.AS | C75: Randstad N.V. | D75: Industrials | E75: Netherlands | F75: 4578835456 | G75: 0.0366 | H75: 0.1745 | I75: 1.79 | J75: 0.0032 | K75: 8.89 | L75: -0.0574 | N75: 317000000 | O75: 9.96 | P75: 2024 | Q75: 24122000000 | R75: 606000000 | S75: 281000000 | T75: 123000000 | U75: 11190000000 | V75: 2218000000 | W75: 357000000 | X75: 1861000000 | Y75: 84000000 | Z75: 46083 | AA75: 27.23 | AB75: 175232895 | AC75: 20.2391 | AD75: 2.1895 | AE75: 8.534 | AF75: -0.7858 | AG75: 20.239082 | AH75: 2.1895186 | AI75: 8.5339978 | AJ75: 11.312688 | AK75: 7.5558341
A76: 55 | B76: UTG.L | C76: Unite Group PLC | D76: Real Estate | E76: United Kingdom | F76: 2647970560 | G76: 1.6104 | H76: -0.0223 | I76: 2.23 | J76: 0.9205 | K76: 14.92 | L76: 0.0401 | N76: 5700000 | O76: 16.52 | P76: 2024 | Q76: 299300000 | R76: 482000000 | S76: 476300000 | T76: 441900000 | U76: 6419900000 | V76: 1346600000 | W76: 273200000 | X76: 1073400000 | Y76: 275500000 | Z76: 46083 | AA76: 500 | AB76: 541221287 | AC76: 10.6964 | AD76: 25 | AE76: 7.7062 | AF76: 0.5633 | AG76: 10.696397 | AH76: 25 | AI76: 7.7061842 | AJ76: 14.090414 | AK76: 5.4937149
A77: 57 | B77: DEC.PA | C77: JCDecaux SE | D77: Communication Services | E77: France | F77: 3479629312 | G77: 0.3715 | H77: 0.2332 | I77: 2.45 | J77: 0.0878 | K77: 7.37 | L77: 0.131 | N77: 862600000 | O77: 8.89 | P77: 2024 | Q77: 3632600000 | R77: 1349400000 | S77: 486800000 | T77: 258900000 | U77: 8615000000 | V77: 4566000000 | W77: 1262400000 | X77: 3303600000 | Y77: 319000000 | Z77: 46080 | AA77: 17.54 | AB77: 212951611 | AC77: 23.0854 | AD77: 13.0739 | AE77: 7.3715 | AF77: -0.6977 | AG77: 23.085402 | AH77: 13.073939 | AI77: 7.3714596 | AJ77: 15.36778 | AK77: 2.5786493
A78: 97 | B78: CON.DE | C78: Continental Aktiengesellschaft | D78: Consumer Cyclical | E78: Germany | F78: 13184394240 | G78: 0.1145 | H78: 0.0743 | I78: 0.91 | J78: 0.0492 | L78: 0.059 | N78: 2211000000 | O78: 7.69 | P78: 2024 | Q78: 39719000000 | R78: 4549000000 | S78: 2338000000 | T78: 1168000000 | U78: 36966000000 | V78: 6878000000 | W78: 2720000000 | X78: 4158000000 | Y78: 1954000000 | Z78: 46085 | AA78: 65.92 | AB78: 200005982 | AC78: 15.3805 | AD78: 4.7213 | AE78: 11.3338 | AF78: -0.3046 | AG78: 15.380459 | AH78: 4.7213081 | AI78: 11.333828 | AJ78: 10.968724 | AK78: 2.8983061
A79: 59 | B79: SRE.L | C79: Sirius Real Estate Limited | D79: Real Estate | E79: Guernsey | F79: 1682595968 | G79: 0.7402 | H79: 0.0423 | I79: 3.33 | J79: 0.1953 | K79: 8.42 | L79: 0.1512 | N79: 5500000 | O79: 20.93 | P79: 2024 | Q79: 288800000 | R79: 140800000 | S79: 135700000 | T79: 107800000 | U79: 2595200000 | V79: 982900000 | W79: 214500000 | X79: 768400000 | Y79: 42600000 | Z79: 46083 | AA79: 111.3641 | AB79: 1505897102 | AC79: 13.8288 | AD79: 25 | AE79: 6.3727 | AF79: -1.0505 | AG79: 13.828803 | AH79: 25 | AI79: 6.372697 | AJ79: 14.94333 | AK79: 11.950255
A80: 76 | B80: COV.PA | C80: Covivio | D80: Real Estate | E80: France | F80: 6343170560 | G80: 0.5221 | H80: 0.0606 | I80: 14.63 | J80: 0.4671 | L80: 0.1465 | N80: 114700000 | O80: 20.81 | P80: 2024 | Q80: 1275500000 | R80: 665900000 | S80: 551200000 | T80: 68100000 | U80: 24888300000 | V80: 10748500000 | W80: 1006900000 | X80: 9741600000 | Y80: 595800000 | Z80: 46085 | AA80: 57.25 | AB80: 110701059 | AC80: 14.7162 | AD80: 17.9685 | AE80: 3.5418 | AF80: -8.0666 | AG80: 14.716156 | AH80: 17.968515 | AI80: 3.5418384 | AJ80: 12.339568 | AK80: 9.5257104
A81: 60 | B81: SPIE.PA | C81: SPIE SA | D81: Industrials | E81: France | F81: 8661908480 | G81: 0.0883 | H81: 0.096 | I81: 2.32 | J81: 0.0089 | L81: 0.1241 | N81: 362019000 | O81: 14.44 | P81: 2024 | Q81: 9919712000 | R81: 875868000 | S81: 513849000 | T81: 273175000 | U81: 9986725000 | V81: 2745514000 | W81: 713637000 | X81: 2031877000 | Y81: 88553000 | Z81: 46085 | AA81: 51.05 | AB81: 170175007 | AC81: 16.4327 | AD81: 3.8698 | AE81: 7.5639 | AF81: -1.1516 | AG81: 16.432676 | AH81: 3.8697948 | AI81: 7.5638896 | AJ81: 10.003176 | AK81: 9.8895136
A82: 102 | B82: DBAN.DE | C82: Deutsche Beteiligungs AG | D82: Financial Services | E82: Germany | F82: 440593376 | G82: 0 | H82: 0.028 | I82: 0 | J82: 0.0066 | L82: -1.8294 | N82: 0 | O82: -3.46 | P82: 2024 | Q82: 107767000 | R82: 0 | S82: 0 | T82: 47514000 | U82: 913687000 | V82: 139003000 | W82: 23966000 | X82: 115037000 | Y82: 714000 | Z82: 46085 | AA82: 24.75 | AB82: 17801751 | AC82: 13.1354 | AD82: 1 | AE82: 19.4117 | AF82: 0.0392 | AG82: 13.135406 | AH82: 1 | AI82: 19.411657 | AJ82: 11.377659 | AK82: #NUM!
A83: 62 | B83: FBK.MI | C83: FinecoBank Banca Fineco S.p.A. | D83: Financial Services | E83: Italy | F83: 11783246848 | G83: 0 | H83: 0.0116 | I83: 0 | J83: 0 | L83: 0.1747 | N83: 25791000 | O83: 0 | Z83: 46085 | AA83: 19.21 | AB83: 611792921 | AC83: 12.3402 | AD83: 1 | AE83: 19.4117 | AF83: 0.0162 | AG83: 12.340182 | AH83: 1 | AI83: 19.411657 | AJ83: 11.05957
A84: 63 | B84: HEI.DE | C84: Heidelberg Materials AG | D84: Basic Materials | E84: Germany | F84: 31683137536 | G84: 0.2101 | H84: 0.0575 | I84: 1.14 | J84: 0.0667 | L84: 0.0433 | N84: 1545000000 | O84: 8.65 | P84: 2024 | Q84: 21156400000 | R84: 4444700000 | S84: 2899700000 | T84: 1781800000 | U84: 37301700000 | V84: 8195900000 | W84: 3120300000 | X84: 5075600000 | Y84: 1410100000 | Z84: 46085 | AA84: 179.5 | AB84: 175968536 | AC84: 14.5658 | AD84: 7.8284 | AE84: 10.3798 | AF84: -0.3514 | AG84: 14.565839 | AH84: 7.8283567 | AI84: 10.379787 | AJ84: 11.288779 | AK84: 7.1282961
A85: 144 | B85: DEMANT.CO | C85: Demant A/S | D85: Healthcare | E85: Denmark | F85: 39902015488 | G85: 0.2252 | H85: 0.0751 | I85: 3.8 | J85: 0.0373 | L85: 0.0529 | N85: 1519000000 | O85: 12.69 | P85: 2024 | Q85: 22419000000 | R85: 5803000000 | S85: 4368000000 | T85: 2387000000 | U85: 32450000000 | V85: 15681000000 | W85: 1112000000 | X85: 14569000000 | Y85: 779000000 | Z85: 46085 | AA85: 189.4 | AB85: 210898609 | AC85: 15.4193 | AD85: 8.3191 | AE85: 5.9893 | AF85: -1.9046 | AG85: 15.41925 | AH85: 8.3191144 | AI85: 5.9892941 | AJ85: 10.460223 | AK85: 6.8761012
A86: 64 | B86: WDP.BR | C86: Warehouses De Pauw SA | D86: Real Estate | E86: Belgium | F86: 5789136896 | G86: 1.0203 | H86: 0.0636 | I86: 0 | J86: 0.0597 | L86: 0.1454 | N86: 12766000 | O86: 20.98 | P86: 2024 | Q86: 438362000 | R86: 523429000 | S86: 511511000 | T86: 435499000 | U86: 8203210000 | V86: 3063752000 | W86: 10374000 | X86: 3053378000 | Y86: 29267000 | Z86: 46085 | AA86: 24.58 | AB86: 235139589 | AC86: 14.8616 | AD86: 25 | AE86: 19.4117 | AF86: 1.3134 | AG86: 14.861624 | AH86: 25 | AI86: 19.411657 | AJ86: 19.268146 | AK86: 11.060023
A87: 65 | B87: ENX.PA | C87: Euronext N.V. | D87: Financial Services | E87: Netherlands | F87: 14257366016 | G87: 0.6871 | H87: 0.0478 | I87: 1.44 | J87: 0.0713 | L87: 0.089 | N87: 199900000 | O87: 14.15 | P87: 2024 | Q87: 1627000000 | R87: 1107600000 | S87: 918900000 | T87: 585600000 | U87: 279101848000 | V87: 3115527000 | W87: 1673455000 | X87: 1442072000 | Y87: 87300000 | Z87: 46085 | AA87: 137.6 | AB87: 101721940 | AC87: 14.0955 | AD87: 23.3311 | AE87: 9.4057 | AF87: 0.0274 | AG87: 14.095494 | AH87: 23.331099 | AI87: 9.4056849 | AJ87: 15.459233 | AK87: 12.872306
A88: 149 | B88: DHER.DE | C88: Delivery Hero SE | D88: Consumer Cyclical | E88: Germany | F88: 5148495872 | G88: 0.0195 | H88: 0.0697 | I88: 7.75 | J88: 0.0227 | L88: 0.2869 | N88: 465400000 | O88: 19 | P88: 2024 | Q88: 12294800000 | R88: 239900000 | S88: -225500000 | T88: -882400000 | U88: 12420400000 | V88: 5667400000 | W88: 3808700000 | X88: 1858700000 | Y88: 279500000 | Z88: 46085 | AA88: 17.255 | AB88: 300116319 | AC88: 15.1574 | AD88: 1.6338 | AE88: 4.3948 | AF88: -4.529 | AG88: 15.157408 | AH88: 1.6337599 | AI88: 4.3947578 | AJ88: 7.8715186 | AK88: 21.461008
A89: 66 | B89: UNI.MC | C89: Unicaja Banco, S.A. | D89: Financial Services | E89: Spain | F89: 6277194752 | G89: 0 | H89: -0.0648 | I89: 0 | J89: 0.0241 | L89: 0.0693 | N89: 86850000 | O89: 0 | Z89: 46085 | AA89: 2.434 | AB89: 2568410415 | AC89: 8.6356 | AD89: 1 | AE89: 19.4117 | AF89: -0.0907 | AG89: 8.6356032 | AH89: 1 | AI89: 19.411657 | AJ89: 9.5777383
A90: 67 | B90: SNR.L | C90: Senior plc | D90: Industrials | E90: United Kingdom | F90: 1219529856 | G90: 0.1157 | H90: 0.0199 | I90: 1.37 | J90: 0.0442 | L90: -0.0289 | N90: 30300000 | O90: 17.59 | P90: 2024 | Q90: 977100000 | R90: 100300000 | S90: 49700000 | T90: 25900000 | U90: 1015800000 | V90: 275100000 | W90: 45500000 | X90: 229600000 | Y90: 43200000 | Z90: 46085 | AA90: 293.5 | AB90: 413399920 | AC90: 12.7426 | AD90: 4.7603 | AE90: 9.6109 | AF90: -0.6553 | AG90: 12.742643 | AH90: 4.7603088 | AI90: 9.6109176 | AJ90: 9.4084252 | AK90: 12.158822
A91: 68 | B91: NXT.L | C91: NEXT plc | D91: Consumer Cyclical | E91: United Kingdom | F91: 15119721472 | G91: 0.2279 | H91: 0.0646 | I91: 1.2 | J91: 0.0257 | L91: 0.0977 | N91: 311000000 | O91: 13 | P91: 2024 | Q91: 5491000000 | R91: 1349300000 | S91: 1103300000 | T91: 802300000 | U91: 4724300000 | V91: 1916700000 | W91: 188300000 | X91: 1728400000 | Y91: 188200000 | Z91: 46085 | AA91: 13040 | AB91: 115726916 | AC91: 14.9101 | AD91: 8.4069 | AE91: 10.1637 | AF91: -0.3561 | AG91: 14.910113 | AH91: 8.4068657 | AI91: 10.163713 | AJ91: 11.535219 | AK91: 11.205604
A92: 166 | B92: DIM.PA | C92: Sartorius Stedim Biotech S.A. | D92: Healthcare | E92: France | F92: 16398235648 | G92: 0.28 | H92: 0.0182 | I92: 2.62 | J92: 0.1325 | L92: -0.0454 | N92: 318100000 | O92: 23.72 | P92: 2024 | Q92: 2780000000 | R92: 670500000 | S92: 368800000 | T92: 175100000 | U92: 8256400000 | V92: 2869600000 | W92: 678900000 | X92: 2190700000 | Y92: 339800000 | Z92: 46085 | AA92: 169 | AB92: 97290030 | AC92: 12.6602 | AD92: 10.1001 | AE92: 7.1407 | AF92: -1.2105 | AG92: 12.660212 | AH92: 10.100142 | AI92: 7.1406745 | AJ92: 10.23633 | AK92: 24.456727
A93: 69 | B93: EVK.DE | C93: Evonik Industries AG | D93: Basic Materials | E93: Germany | F93: 6304979968 | G93: 0.1163 | H93: 0.1385 | I93: 1.88 | J93: 0.0554 | L93: 0.0183 | N93: 1117000000 | O93: 4.63 | P93: 2024 | Q93: 15157000000 | R93: 1763000000 | S93: 646000000 | T93: 222000000 | U93: 19750000000 | V93: 3781000000 | W93: 461000000 | X93: 3320000000 | Y93: 840000000 | Z93: 46085 | AA93: 13.56 | AB93: 466000000 | AC93: 18.4935 | AD93: 4.7798 | AE93: 8.3441 | AF93: -0.7945 | AG93: 18.493469 | AH93: 4.7798091 | AI93: 8.3440946 | AJ93: 11.334559 | AK93: 3.5762791
A94: 71 | B94: SBMO.AS | C94: SBM Offshore N.V. | D94: Energy | E94: Netherlands | F94: 5230405120 | G94: 0.3473 | H94: 0.2189 | I94: 3.94 | J94: 0.0242 | L94: 0.0693 | N94: 66000000 | O94: 13.4 | P94: 2024 | Q94: 4784000000 | R94: 1200000000 | S94: 1130000000 | T94: 150000000 | U94: 17157000000 | V94: 8943000000 | W94: 806000000 | X94: 8137000000 | Y94: 116000000 | Z94: 46085 | AA94: 31.18 | AB94: 167964206 | AC94: 22.392 | AD94: 12.2874 | AE94: 5.8892 | AF94: -1.6408 | AG94: 22.392005 | AH94: 12.287426 | AI94: 5.8891913 | AJ94: 14.409787 | AK94: 4.3586709
A95: 72 | B95: G1A.DE | C95: GEA Group Aktiengesellschaft | D95: Industrials | E95: Germany | F95: 10062724096 | G95: 0.1463 | H95: 0.047 | I95: -0.41 | J95: 0.0437 | L95: 0.0492 | N95: 219089000 | O95: 13.97 | P95: 2024 | Q95: 5422129000 | R95: 793508000 | S95: 574419000 | T95: 385043000 | U95: 6032165000 | V95: 294776000 | W95: 620915000 | X95: -326139000 | Y95: 237105000 | Z95: 46085 | AA95: 62.55 | AB95: 160618100 | AC95: 14.0567 | AD95: 5.7548 | AE95: 25 | AF95: 0.4874 | AG95: 14.056702 | AH95: 5.7548243 | AI95: 25 | AJ95: 14.849128 | AK95: 12.681314
A96: 73 | B96: DOM.ST | C96: Dometic Group AB (publ) | D96: Consumer Cyclical | E96: Sweden | F96: 11131379712 | G96: 0.1529 | H96: 0.2225 | I96: 3.61 | J96: 0.0172 | L96: -0.1086 | N96: 1310000000 | O96: 7.51 | P96: 2024 | Q96: 24620000000 | R96: 2538000000 | S96: -972000000 | T96: -2303000000 | U96: 52822000000 | V96: 17624000000 | W96: 4213000000 | X96: 13411000000 | Y96: 379000000 | Z96: 46085 | AA96: 34.98 | AB96: 319499993 | AC96: 22.5666 | AD96: 5.9693 | AE96: 6.1349 | AF96: -1.671 | AG96: 22.566567 | AH96: 5.9693276 | AI96: 6.1348729 | AJ96: 12.657887 | AK96: 4.3858864
A97: 74 | B97: TEL.OL | C97: Telenor ASA | D97: Communication Services | E97: Norway | F97: 236779782144 | G97: 0.4864 | H97: 0.0815 | I97: 0.3 | J97: 0.1558 | L97: -0.0004 | N97: 17304000000 | O97: 9.18 | P97: 2024 | Q97: 75487000000 | R97: 44273000000 | S97: 27329000000 | T97: 18336000000 | U97: 228808000000 | V97: 99889000000 | W97: 10369000000 | X97: 89520000000 | Y97: 13383000000 | Z97: 46085 | AA97: 173 | AB97: 1367795415 | AC97: 15.7296 | AD97: 16.8082 | AE97: 15.4991 | AF97: 0.5178 | AG97: 15.729581 | AH97: 16.808247 | AI97: 15.499065 | AJ97: 15.984026 | AK97: 5.3481757
A98: 78 | B98: DUE.DE | C98: Dürr Aktiengesellschaft | D98: Industrials | E98: Germany | F98: 1518985728 | G98: 0.0806 | H98: 0.1517 | I98: 1.43 | J98: 0.0359 | L98: 0.0717 | N98: 162321000 | O98: 8.01 | P98: 2024 | Q98: 4290936000 | R98: 345838000 | S98: 183517000 | T98: 101524000 | U98: 4978375000 | V98: 1325211000 | W98: 831585000 | X98: 493626000 | Y98: 153853000 | Z98: 46085 | AA98: 22 | AB98: 69202080 | AC98: 19.1335 | AD98: 3.6195 | AE98: 9.4343 | AF98: -0.5489 | AG98: 19.133527 | AH98: 3.6195409 | AI98: 9.4342799 | AJ98: 11.569557 | AK98: 4.3921886
A99: 75 | B99: IDR.MC | C99: Indra Sistemas, S.A. | D99: Technology | E99: Spain | F99: 10723998720 | G99: 0.1126 | H99: 0.0317 | I99: 0.54 | J99: 0.0229 | L99: 0.1232 | N99: 119035000 | O99: 18.13 | P99: 2024 | Q99: 4842857000 | R99: 545285000 | S99: 438335000 | T99: 277541000 | U99: 4955684000 | V99: 850874000 | W99: 555147000 | X99: 295727000 | Y99: 111000000 | Z99: 46085 | AA99: 60.55 | AB99: 175228738 | AC99: 13.3148 | AD99: 4.6596 | AE99: 13.4666 | AF99: -0.1445 | AG99: 13.314816 | AH99: 4.6595572 | AI99: 13.46655 | AJ99: 10.763759 | AK99: 19.666777
A100: 86 | B100: EBRO.MC | C100: Ebro Foods, S.A. | D100: Consumer Defensive | E100: Spain | F100: 2929597184 | G100: 0.1377 | H100: 0.0477 | I100: 0.6 | J100: 0.0473 | L100: 0.0057 | N100: 0 | O100: 8.26 | P100: 2024 | Q100: 3140493000 | R100: 432558000 | S100: 324204000 | T100: 207867000 | U100: 4010946000 | V100: 510418000 | W100: 249885000 | X100: 260533000 | Y100: 148634000 | Z100: 46085 | AA100: 19.04 | AB100: 153820392 | AC100: 14.0906 | AD100: 5.4753 | AE100: 13.0537 | AF100: -0.128 | AG100: 14.090645 | AH100: 5.4753199 | AI100: 13.053695 | AJ100: 11.194962 | AK100: 6.7727269
...

Sheet country_tax
A1: country_name | B1: tax_rate
A2: United States | B2: 0.21
A3: France | B3: 0.25
A4: Germany | B4: 0.299
A5: United Kingdom | B5: 0.25
A6: Canada | B6: 0.265
A7: Brazil | B7: 0.34
A8: Belgium | B8: 0.25
A9: Bermuda | B9: 0
A10: Denmark | B10: 0.22
A11: Guernsey | B11: 0
A12: Hungary | B12: 0.09
A13: Italy | B13: 0.24
... A19: Switzerland | B19: 0.148

Sheet sector_benchmarks
A1: sector | B1: target_ebitda_mult | C1: annual_growth | D1: max_leverage | E1: nwc_variation_revenue | F1: capex_to_revenue | G1: ebitda_margin_target | H1: sector_beta
A2: Technology | B2: 15.5 | C2: 0.12 | D2: 3 | E2: 0.02 | F2: 0.04 | G2: 0.25 | H2: 1.2
A3: Healthcare | B3: 13 | C3: 0.07 | D3: 4 | E3: 0.03 | F3: 0.05 | G3: 0.2 | H3: 0.85
A4: Communication Services | B4: 9 | C4: 0.04 | D4: 4.5 | E4: 0.01 | F4: 0.12 | G4: 0.3 | H4: 1.05
A5: Consumer Cyclical | B5: 10.5 | C5: 0.05 | D5: 3.5 | E5: 0.06 | F5: 0.03 | G5: 0.15 | H5: 1.15
A6: Consumer Defensive | B6: 11 | C6: 0.03 | D6: 4.5 | E6: 0.04 | F6: 0.025 | G6: 0.12 | H6: 0.65
A7: Financial Services | B7: 10 | C7: 0.04 | D7: 7 | E7: 0 | F7: 0.01 | G7: 0.4 | H7: 1.1
A8: Industrials | B8: 9.5 | C8: 0.035 | D8: 3.5 | E8: 0.08 | F8: 0.06 | G8: 0.18 | H8: 1
A9: Energy | B9: 6 | C9: 0.02 | D9: 2.5 | E9: 0.03 | F9: 0.15 | G9: 0.35 | H9: 1.1
A10: Basic Materials | B10: 7.5 | C10: 0.025 | D10: 3 | E10: 0.1 | F10: 0.08 | G10: 0.22 | H10: 1.25
A11: Real Estate | B11: 16 | C11: 0.03 | D11: 8 | E11: 0.01 | F11: 0.05 | G11: 0.6 | H11: 0.7
A12: Utilities | B12: 10 | C12: 0.02 | D12: 6 | E12: 0.02 | F12: 0.2 | G12: 0.38 | H12: 0.5
